systolic_array_32x32x3_16filters_read_vertically/ifm_shift_RF.v
module ifm_shift_RF #(
    parameter DATA_WIDTH  = 8  , 
    parameter BUFFER_SIZE = 27
) (
	input                           clk               ,
	input                           rst_n             ,
    input                           ifm_demux         ,
	input                           ifm_mux           ,
    input                           ifm_RF_shift_en_1 ,
    input                           ifm_RF_shift_en_2 ,    
	input      [DATA_WIDTH - 1 : 0] data_in           ,
	output reg [DATA_WIDTH - 1 : 0] data_out
);

	reg [DATA_WIDTH - 1 : 0] buffer_1 [0 : BUFFER_SIZE - 1] ;
	reg [DATA_WIDTH - 1 : 0] buffer_2 [0 : BUFFER_SIZE - 1] ;

	integer i;

    always @(posedge clk or negedge rst_n) begin
        if (!rst_n) begin
			data_out        <= 0;
			for (i = 0; i < BUFFER_SIZE; i = i + 1) begin
				buffer_1[i] <= 0;
                buffer_2[i] <= 0;
			end
        end
        else begin
            data_out <= (ifm_mux == 0) ? ((ifm_RF_shift_en_1) ? buffer_1[BUFFER_SIZE - 1] : data_out) : ((ifm_RF_shift_en_2) ? buffer_2[BUFFER_SIZE - 1] : data_out);
            for (i = BUFFER_SIZE - 1; i > 0; i = i - 1) begin
                buffer_1[i] <= (ifm_RF_shift_en_1) ? buffer_1[i-1] : buffer_1[i];
                buffer_2[i] <= (ifm_RF_shift_en_2) ? buffer_2[i-1] : buffer_2[i];
            end
            buffer_1[0] <= (ifm_RF_shift_en_1) ? ((ifm_demux == 0) ? data_in : 0) : buffer_1[0];
            buffer_2[0] <= (ifm_RF_shift_en_2) ? ((ifm_demux == 1) ? data_in : 0) : buffer_2[0];
        end 
    end

endmodule

systolic_array_layer0/ifm_shift_RF_tb.v
module ifm_shift_RF_tb();

parameter DATA_WIDTH  = 8 ;
parameter BUFFER_SIZE = 5 ;

reg                       clk               ;
reg                       rst_n             ;
reg                       ifm_demux         ;
reg                       ifm_mux           ;
reg                       ifm_RF_shift_en_1 ;
reg                       ifm_RF_shift_en_2 ;
reg  [DATA_WIDTH - 1 : 0] data_in           ;
wire [DATA_WIDTH - 1 : 0] data_out          ;

ifm_shift_RF #(
    .DATA_WIDTH  ( DATA_WIDTH  ) ,
    .BUFFER_SIZE ( BUFFER_SIZE )
) ifm_shift_RF_dut ( 
    .clk               ( clk               ) ,
    .rst_n             ( rst_n             ) ,
    .ifm_demux         ( ifm_demux         ) ,
    .ifm_mux           ( ifm_mux           ) ,
    .ifm_RF_shift_en_1 ( ifm_RF_shift_en_1 ) ,
    .ifm_RF_shift_en_2 ( ifm_RF_shift_en_2 ) ,
    .data_in           ( data_in           ) ,
    .data_out          ( data_out          )
);

always #5 clk = ~clk;

integer i;

initial begin
    clk = 0;
    rst_n = 0;
    
    ifm_demux = 0;
    ifm_mux = 1;
    ifm_RF_shift_en_1 = 1;
    ifm_RF_shift_en_2 = 1;

    data_in = 1;

    #30 rst_n = 1; 
    
    for (i = 2; i < 7; i = i + 1) begin
        data_in = i;
        #10;
    end

    #10 
    ifm_demux = 1;
    ifm_mux = 0;

    #30 ifm_RF_shift_en_1 = 0;

    for (i = 12; i < 17; i = i + 1) begin
        data_in = i;
        #10;
    end

    #20 
    ifm_RF_shift_en_1 = 1;
    ifm_RF_shift_en_2 = 0;

    for (i = 22; i < 27; i = i + 1) begin
        data_in = i;
        #10;
    end

    ifm_RF_shift_en_1 = 1;
    ifm_RF_shift_en_2 = 1;

    for (i = 30; i < 33; i = i + 1) begin
        data_in = i;
        #10;
    end

    #500 $finish;
end

initial begin
    $dumpfile ("ifm_shift_RF.VCD");
    $dumpvars (0, ifm_shift_RF_tb);

    $dumpvars (0, ifm_shift_RF_dut.buffer_1[0]);
    $dumpvars (0, ifm_shift_RF_dut.buffer_1[1]);
    $dumpvars (0, ifm_shift_RF_dut.buffer_1[2]);
    $dumpvars (0, ifm_shift_RF_dut.buffer_1[3]);
    $dumpvars (0, ifm_shift_RF_dut.buffer_1[4]);

    $dumpvars (0, ifm_shift_RF_dut.buffer_2[0]);
    $dumpvars (0, ifm_shift_RF_dut.buffer_2[1]);
    $dumpvars (0, ifm_shift_RF_dut.buffer_2[2]);
    $dumpvars (0, ifm_shift_RF_dut.buffer_2[3]);
    $dumpvars (0, ifm_shift_RF_dut.buffer_2[4]);

/*  $dumpvars (0, wgt_shift_RF_dut.buffer[5]);
    $dumpvars (0, wgt_shift_RF_dut.buffer[6]);
    $dumpvars (0, wgt_shift_RF_dut.buffer[7]);
    $dumpvars (0, wgt_shift_RF_dut.buffer[8]);
    $dumpvars (0, wgt_shift_RF_dut.buffer[9]);
    $dumpvars (0, wgt_shift_RF_dut.buffer[10]);
    $dumpvars (0, wgt_shift_RF_dut.buffer[11]);
    $dumpvars (0, wgt_shift_RF_dut.buffer[12]);
    $dumpvars (0, wgt_shift_RF_dut.buffer[13]);
    $dumpvars (0, wgt_shift_RF_dut.buffer[14]);
    $dumpvars (0, wgt_shift_RF_dut.buffer[15]);
    $dumpvars (0, wgt_shift_RF_dut.buffer[16]);
    $dumpvars (0, wgt_shift_RF_dut.buffer[17]);
    $dumpvars (0, wgt_shift_RF_dut.buffer[18]);
    $dumpvars (0, wgt_shift_RF_dut.buffer[19]);
    $dumpvars (0, wgt_shift_RF_dut.buffer[20]);
    $dumpvars (0, wgt_shift_RF_dut.buffer[21]);
    $dumpvars (0, wgt_shift_RF_dut.buffer[22]);
    $dumpvars (0, wgt_shift_RF_dut.buffer[23]);
    $dumpvars (0, wgt_shift_RF_dut.buffer[24]);
    $dumpvars (0, wgt_shift_RF_dut.buffer[25]);
    $dumpvars (0, wgt_shift_RF_dut.buffer[26]);*/
end

endmodule

systolic_array_layer0/ifm_shift_RF.VCD
$date
	Sat Mar 22 01:34:09 2025
$end
$version
	Icarus Verilog
$end
$timescale
	1s
$end
$scope module ifm_shift_RF_tb $end
$var wire 8 ! data_out [7:0] $end
$var parameter 32 " BUFFER_SIZE $end
$var parameter 32 # DATA_WIDTH $end
$var reg 1 $ clk $end
$var reg 8 % data_in [7:0] $end
$var reg 1 & ifm_RF_shift_en_1 $end
$var reg 1 ' ifm_RF_shift_en_2 $end
$var reg 1 ( ifm_demux $end
$var reg 1 ) ifm_mux $end
$var reg 1 * rst_n $end
$var integer 32 + i [31:0] $end
$scope module ifm_shift_RF_dut $end
$var wire 1 $ clk $end
$var wire 8 , data_in [7:0] $end
$var wire 1 & ifm_RF_shift_en_1 $end
$var wire 1 ' ifm_RF_shift_en_2 $end
$var wire 1 ( ifm_demux $end
$var wire 1 ) ifm_mux $end
$var wire 1 * rst_n $end
$var parameter 32 - BUFFER_SIZE $end
$var parameter 32 . DATA_WIDTH $end
$var reg 8 / data_out [7:0] $end
$var integer 32 0 i [31:0] $end
$upscope $end
$upscope $end
$scope module ifm_shift_RF_tb $end
$scope module ifm_shift_RF_dut $end
$var reg 8 1 \buffer_1[0] [7:0] $end
$upscope $end
$upscope $end
$scope module ifm_shift_RF_tb $end
$scope module ifm_shift_RF_dut $end
$var reg 8 2 \buffer_1[1] [7:0] $end
$upscope $end
$upscope $end
$scope module ifm_shift_RF_tb $end
$scope module ifm_shift_RF_dut $end
$var reg 8 3 \buffer_1[2] [7:0] $end
$upscope $end
$upscope $end
$scope module ifm_shift_RF_tb $end
$scope module ifm_shift_RF_dut $end
$var reg 8 4 \buffer_1[3] [7:0] $end
$upscope $end
$upscope $end
$scope module ifm_shift_RF_tb $end
$scope module ifm_shift_RF_dut $end
$var reg 8 5 \buffer_1[4] [7:0] $end
$upscope $end
$upscope $end
$scope module ifm_shift_RF_tb $end
$scope module ifm_shift_RF_dut $end
$var reg 8 6 \buffer_2[0] [7:0] $end
$upscope $end
$upscope $end
$scope module ifm_shift_RF_tb $end
$scope module ifm_shift_RF_dut $end
$var reg 8 7 \buffer_2[1] [7:0] $end
$upscope $end
$upscope $end
$scope module ifm_shift_RF_tb $end
$scope module ifm_shift_RF_dut $end
$var reg 8 8 \buffer_2[2] [7:0] $end
$upscope $end
$upscope $end
$scope module ifm_shift_RF_tb $end
$scope module ifm_shift_RF_dut $end
$var reg 8 9 \buffer_2[3] [7:0] $end
$upscope $end
$upscope $end
$scope module ifm_shift_RF_tb $end
$scope module ifm_shift_RF_dut $end
$var reg 8 : \buffer_2[4] [7:0] $end
$upscope $end
$upscope $end
$enddefinitions $end
$comment Show the parameter values. $end
$dumpall
b1000 .
b101 -
b1000 #
b101 "
$end
#0
$dumpvars
b0 :
b0 9
b0 8
b0 7
b0 6
b0 5
b0 4
b0 3
b0 2
b0 1
b101 0
b0 /
b1 ,
bx +
0*
1)
0(
1'
1&
b1 %
0$
b0 !
$end
#5
b0 :
b0 5
b0 9
b0 4
b0 8
b0 3
b0 7
b0 2
b0 6
b0 1
b101 0
1$
#10
0$
#15
b0 :
b0 5
b0 9
b0 4
b0 8
b0 3
b0 7
b0 2
b0 6
b0 1
b101 0
1$
#20
0$
#25
b0 :
b0 5
b0 9
b0 4
b0 8
b0 3
b0 7
b0 2
b0 6
b0 1
b101 0
1$
#30
0$
b10 %
b10 ,
b10 +
1*
#35
b0 6
b10 1
b0 7
b0 2
b0 8
b0 3
b0 9
b0 4
b0 :
b0 5
b0 0
1$
#40
0$
b11 %
b11 ,
b11 +
#45
b0 6
b11 1
b0 7
b10 2
b0 8
b0 3
b0 9
b0 4
b0 :
b0 5
b0 0
1$
#50
0$
b100 %
b100 ,
b100 +
#55
b0 6
b100 1
b0 7
b11 2
b0 8
b10 3
b0 9
b0 4
b0 :
b0 5
b0 0
1$
#60
0$
b101 %
b101 ,
b101 +
#65
b0 6
b101 1
b0 7
b100 2
b0 8
b11 3
b0 9
b10 4
b0 :
b0 5
b0 0
1$
#70
0$
b110 %
b110 ,
b110 +
#75
b0 6
b110 1
b0 7
b101 2
b0 8
b100 3
b0 9
b11 4
b0 :
b10 5
b0 0
1$
#80
0$
b111 +
#85
b0 6
b110 1
b0 7
b110 2
b0 8
b101 3
b0 9
b100 4
b0 :
b11 5
b0 0
1$
#90
0$
0)
1(
#95
b110 6
b0 1
b0 7
b110 2
b0 8
b110 3
b0 9
b101 4
b0 :
b100 5
b11 !
b11 /
b0 0
1$
#100
0$
#105
b110 6
b0 1
b110 7
b0 2
b0 8
b110 3
b0 9
b110 4
b0 :
b101 5
b100 !
b100 /
b0 0
1$
#110
0$
#115
b110 6
b0 1
b110 7
b0 2
b110 8
b0 3
b0 9
b110 4
b0 :
b110 5
b101 !
b101 /
b0 0
1$
#120
0$
b1100 %
b1100 ,
b1100 +
0&
#125
b1100 6
b0 1
b110 7
b0 2
b110 8
b0 3
b110 9
b110 4
b0 :
b110 5
b0 0
1$
#130
0$
b1101 %
b1101 ,
b1101 +
#135
b1101 6
b0 1
b1100 7
b0 2
b110 8
b0 3
b110 9
b110 4
b110 :
b110 5
b0 0
1$
#140
0$
b1110 %
b1110 ,
b1110 +
#145
b1110 6
b0 1
b1101 7
b0 2
b1100 8
b0 3
b110 9
b110 4
b110 :
b110 5
b0 0
1$
#150
0$
b1111 %
b1111 ,
b1111 +
#155
b1111 6
b0 1
b1110 7
b0 2
b1101 8
b0 3
b1100 9
b110 4
b110 :
b110 5
b0 0
1$
#160
0$
b10000 %
b10000 ,
b10000 +
#165
b10000 6
b0 1
b1111 7
b0 2
b1110 8
b0 3
b1101 9
b110 4
b1100 :
b110 5
b0 0
1$
#170
0$
b10001 +
#175
b10000 6
b0 1
b10000 7
b0 2
b1111 8
b0 3
b1110 9
b110 4
b1101 :
b110 5
b0 0
1$
#180
0$
#185
b10000 6
b0 1
b10000 7
b0 2
b10000 8
b0 3
b1111 9
b110 4
b1110 :
b110 5
b0 0
1$
#190
0$
b10110 %
b10110 ,
b10110 +
0'
1&
#195
b10000 6
b0 1
b10000 7
b0 2
b10000 8
b0 3
b1111 9
b0 4
b1110 :
b110 5
b110 !
b110 /
b0 0
1$
#200
0$
b10111 %
b10111 ,
b10111 +
#205
b10000 6
b0 1
b10000 7
b0 2
b10000 8
b0 3
b1111 9
b0 4
b1110 :
b0 5
b0 0
1$
#210
0$
b11000 %
b11000 ,
b11000 +
#215
b10000 6
b0 1
b10000 7
b0 2
b10000 8
b0 3
b1111 9
b0 4
b1110 :
b0 5
b0 !
b0 /
b0 0
1$
#220
0$
b11001 %
b11001 ,
b11001 +
#225
b10000 6
b0 1
b10000 7
b0 2
b10000 8
b0 3
b1111 9
b0 4
b1110 :
b0 5
b0 0
1$
#230
0$
b11010 %
b11010 ,
b11010 +
#235
b10000 6
b0 1
b10000 7
b0 2
b10000 8
b0 3
b1111 9
b0 4
b1110 :
b0 5
b0 0
1$
#240
0$
b11110 %
b11110 ,
1'
b11110 +
#245
b11110 6
b0 1
b10000 7
b0 2
b10000 8
b0 3
b10000 9
b0 4
b1111 :
b0 5
b0 0
1$
#250
0$
b11111 %
b11111 ,
b11111 +
#255
b11111 6
b0 1
b11110 7
b0 2
b10000 8
b0 3
b10000 9
b0 4
b10000 :
b0 5
b0 0
1$
#260
0$
b100000 %
b100000 ,
b100000 +
#265
b100000 6
b0 1
b11111 7
b0 2
b11110 8
b0 3
b10000 9
b0 4
b10000 :
b0 5
b0 0
1$
#270
0$
b100001 +
#275
b100000 6
b0 1
b100000 7
b0 2
b11111 8
b0 3
b11110 9
b0 4
b10000 :
b0 5
b0 0
1$
#280
0$
#285
b100000 6
b0 1
b100000 7
b0 2
b100000 8
b0 3
b11111 9
b0 4
b11110 :
b0 5
b0 0
1$
#290
0$
#295
b100000 6
b0 1
b100000 7
b0 2
b100000 8
b0 3
b100000 9
b0 4
b11111 :
b0 5
b0 0
1$
#300
0$
#305
b100000 6
b0 1
b100000 7
b0 2
b100000 8
b0 3
b100000 9
b0 4
b100000 :
b0 5
b0 0
1$
#310
0$
#315
b100000 6
b0 1
b100000 7
b0 2
b100000 8
b0 3
b100000 9
b0 4
b100000 :
b0 5
b0 0
1$
#320
0$
#325
b100000 6
b0 1
b100000 7
b0 2
b100000 8
b0 3
b100000 9
b0 4
b100000 :
b0 5
b0 0
1$
#330
0$
#335
b100000 6
b0 1
b100000 7
b0 2
b100000 8
b0 3
b100000 9
b0 4
b100000 :
b0 5
b0 0
1$
#340
0$
#345
b100000 6
b0 1
b100000 7
b0 2
b100000 8
b0 3
b100000 9
b0 4
b100000 :
b0 5
b0 0
1$
#350
0$
#355
b100000 6
b0 1
b100000 7
b0 2
b100000 8
b0 3
b100000 9
b0 4
b100000 :
b0 5
b0 0
1$
#360
0$
#365
b100000 6
b0 1
b100000 7
b0 2
b100000 8
b0 3
b100000 9
b0 4
b100000 :
b0 5
b0 0
1$
#370
0$
#375
b100000 6
b0 1
b100000 7
b0 2
b100000 8
b0 3
b100000 9
b0 4
b100000 :
b0 5
b0 0
1$
#380
0$
#385
b100000 6
b0 1
b100000 7
b0 2
b100000 8
b0 3
b100000 9
b0 4
b100000 :
b0 5
b0 0
1$
#390
0$
#395
b100000 6
b0 1
b100000 7
b0 2
b100000 8
b0 3
b100000 9
b0 4
b100000 :
b0 5
b0 0
1$
#400
0$
#405
b100000 6
b0 1
b100000 7
b0 2
b100000 8
b0 3
b100000 9
b0 4
b100000 :
b0 5
b0 0
1$
#410
0$
#415
b100000 6
b0 1
b100000 7
b0 2
b100000 8
b0 3
b100000 9
b0 4
b100000 :
b0 5
b0 0
1$
#420
0$
#425
b100000 6
b0 1
b100000 7
b0 2
b100000 8
b0 3
b100000 9
b0 4
b100000 :
b0 5
b0 0
1$
#430
0$
#435
b100000 6
b0 1
b100000 7
b0 2
b100000 8
b0 3
b100000 9
b0 4
b100000 :
b0 5
b0 0
1$
#440
0$
#445
b100000 6
b0 1
b100000 7
b0 2
b100000 8
b0 3
b100000 9
b0 4
b100000 :
b0 5
b0 0
1$
#450
0$
#455
b100000 6
b0 1
b100000 7
b0 2
b100000 8
b0 3
b100000 9
b0 4
b100000 :
b0 5
b0 0
1$
#460
0$
#465
b100000 6
b0 1
b100000 7
b0 2
b100000 8
b0 3
b100000 9
b0 4
b100000 :
b0 5
b0 0
1$
#470
0$
#475
b100000 6
b0 1
b100000 7
b0 2
b100000 8
b0 3
b100000 9
b0 4
b100000 :
b0 5
b0 0
1$
#480
0$
#485
b100000 6
b0 1
b100000 7
b0 2
b100000 8
b0 3
b100000 9
b0 4
b100000 :
b0 5
b0 0
1$
#490
0$
#495
b100000 6
b0 1
b100000 7
b0 2
b100000 8
b0 3
b100000 9
b0 4
b100000 :
b0 5
b0 0
1$
#500
0$
#505
b100000 6
b0 1
b100000 7
b0 2
b100000 8
b0 3
b100000 9
b0 4
b100000 :
b0 5
b0 0
1$
#510
0$
#515
b100000 6
b0 1
b100000 7
b0 2
b100000 8
b0 3
b100000 9
b0 4
b100000 :
b0 5
b0 0
1$
#520
0$
#525
b100000 6
b0 1
b100000 7
b0 2
b100000 8
b0 3
b100000 9
b0 4
b100000 :
b0 5
b0 0
1$
#530
0$
#535
b100000 6
b0 1
b100000 7
b0 2
b100000 8
b0 3
b100000 9
b0 4
b100000 :
b0 5
b0 0
1$
#540
0$
#545
b100000 6
b0 1
b100000 7
b0 2
b100000 8
b0 3
b100000 9
b0 4
b100000 :
b0 5
b0 0
1$
#550
0$
#555
b100000 6
b0 1
b100000 7
b0 2
b100000 8
b0 3
b100000 9
b0 4
b100000 :
b0 5
b0 0
1$
#560
0$
#565
b100000 6
b0 1
b100000 7
b0 2
b100000 8
b0 3
b100000 9
b0 4
b100000 :
b0 5
b0 0
1$
#570
0$
#575
b100000 6
b0 1
b100000 7
b0 2
b100000 8
b0 3
b100000 9
b0 4
b100000 :
b0 5
b0 0
1$
#580
0$
#585
b100000 6
b0 1
b100000 7
b0 2
b100000 8
b0 3
b100000 9
b0 4
b100000 :
b0 5
b0 0
1$
#590
0$
#595
b100000 6
b0 1
b100000 7
b0 2
b100000 8
b0 3
b100000 9
b0 4
b100000 :
b0 5
b0 0
1$
#600
0$
#605
b100000 6
b0 1
b100000 7
b0 2
b100000 8
b0 3
b100000 9
b0 4
b100000 :
b0 5
b0 0
1$
#610
0$
#615
b100000 6
b0 1
b100000 7
b0 2
b100000 8
b0 3
b100000 9
b0 4
b100000 :
b0 5
b0 0
1$
#620
0$
#625
b100000 6
b0 1
b100000 7
b0 2
b100000 8
b0 3
b100000 9
b0 4
b100000 :
b0 5
b0 0
1$
#630
0$
#635
b100000 6
b0 1
b100000 7
b0 2
b100000 8
b0 3
b100000 9
b0 4
b100000 :
b0 5
b0 0
1$
#640
0$
#645
b100000 6
b0 1
b100000 7
b0 2
b100000 8
b0 3
b100000 9
b0 4
b100000 :
b0 5
b0 0
1$
#650
0$
#655
b100000 6
b0 1
b100000 7
b0 2
b100000 8
b0 3
b100000 9
b0 4
b100000 :
b0 5
b0 0
1$
#660
0$
#665
b100000 6
b0 1
b100000 7
b0 2
b100000 8
b0 3
b100000 9
b0 4
b100000 :
b0 5
b0 0
1$
#670
0$
#675
b100000 6
b0 1
b100000 7
b0 2
b100000 8
b0 3
b100000 9
b0 4
b100000 :
b0 5
b0 0
1$
#680
0$
#685
b100000 6
b0 1
b100000 7
b0 2
b100000 8
b0 3
b100000 9
b0 4
b100000 :
b0 5
b0 0
1$
#690
0$
#695
b100000 6
b0 1
b100000 7
b0 2
b100000 8
b0 3
b100000 9
b0 4
b100000 :
b0 5
b0 0
1$
#700
0$
#705
b100000 6
b0 1
b100000 7
b0 2
b100000 8
b0 3
b100000 9
b0 4
b100000 :
b0 5
b0 0
1$
#710
0$
#715
b100000 6
b0 1
b100000 7
b0 2
b100000 8
b0 3
b100000 9
b0 4
b100000 :
b0 5
b0 0
1$
#720
0$
#725
b100000 6
b0 1
b100000 7
b0 2
b100000 8
b0 3
b100000 9
b0 4
b100000 :
b0 5
b0 0
1$
#730
0$
#735
b100000 6
b0 1
b100000 7
b0 2
b100000 8
b0 3
b100000 9
b0 4
b100000 :
b0 5
b0 0
1$
#740
0$
#745
b100000 6
b0 1
b100000 7
b0 2
b100000 8
b0 3
b100000 9
b0 4
b100000 :
b0 5
b0 0
1$
#750
0$
#755
b100000 6
b0 1
b100000 7
b0 2
b100000 8
b0 3
b100000 9
b0 4
b100000 :
b0 5
b0 0
1$
#760
0$
#765
b100000 6
b0 1
b100000 7
b0 2
b100000 8
b0 3
b100000 9
b0 4
b100000 :
b0 5
b0 0
1$
