systolic_array_layer0/main_controller.v
module main_controller #(
    parameter NO_FILTER     = 16 ,
    parameter KERNEL_SIZE   = 3  ,
    parameter NO_CHANNEL    = 3  ,
    parameter SYSTOLIC_SIZE = 16
) (
    input                              clk                                  , 
    input                              rst_n                                ,
    input                              start                                ,
    output reg                         load_ifm, load_wgt                   ,
    output reg                         ifm_demux, ifm_mux                   ,
    output reg                         ifm_RF_shift_en_1, ifm_RF_shift_en_2 ,
    output reg [SYSTOLIC_SIZE - 1 : 0] wgt_RF_shift_en                      ,
    output reg                         select_wgt                           ,
    output reg                         reset_pe                             ,
    output reg                         write_out_en                          
);

    localparam NO_CYCLE_LOAD    = KERNEL_SIZE * KERNEL_SIZE * NO_CHANNEL;
    localparam NO_CYCLE_COMPUTE = NO_CYCLE_LOAD + SYSTOLIC_SIZE*2 - 1;
    localparam NO_LOAD_FILTER   = (NO_FILTER + SYSTOLIC_SIZE - 1) / SYSTOLIC_SIZE;

    parameter IDLE               = 3'b000 ;
    parameter LOAD_WEIGHT        = 3'b001 ;
    parameter LOAD_COMPUTE       = 3'b010 ;
    parameter LOAD_COMPUTE_WRITE = 3'b011 ; 
    parameter COMPUTE_WRITE      = 3'b100 ;
    parameter WRITE              = 3'b101 ;

    reg [2:0] current_state, next_state;

    reg [4:0]  count_load      ;
    reg [5:0]  count_compute_1 ;
    reg [5:0]  count_compute_2 ;
    reg [4:0]  count_write     ;
    reg [13:0] count_tiling    ;
    reg [2:0]  count_filter    ;

    always @(posedge clk or negedge rst_n) begin
        if (!rst_n) current_state <= IDLE;
        else        current_state <= next_state;
    end

    always @(*) begin
        case (current_state)
            IDLE:               if (start)                               next_state = LOAD_WEIGHT;
            LOAD_WEIGHT:        if (count_load == NO_CYCLE_LOAD)         next_state = LOAD_COMPUTE;
            LOAD_COMPUTE:       if (count_compute_1 == NO_CYCLE_COMPUTE) next_state = LOAD_COMPUTE_WRITE;
            LOAD_COMPUTE_WRITE: if (count_tiling == 3)                   next_state = COMPUTE_WRITE;   // 414*26 = 10764
            COMPUTE_WRITE:      if (count_compute_1 == NO_CYCLE_COMPUTE) next_state = WRITE;
            WRITE: begin 
                if      (count_write == SYSTOLIC_SIZE && count_filter < NO_LOAD_FILTER) next_state = LOAD_WEIGHT;
                else if (count_write == SYSTOLIC_SIZE)                                  next_state = IDLE;
            end
            default: next_state = IDLE;
        endcase
    end

    integer i;

    always @(posedge clk or negedge rst_n) begin
        if (!rst_n) begin
            count_load        <= 0 ;
            count_compute_1   <= 0 ;
            count_compute_2   <= 0 ;
            count_write       <= 0 ;
            count_tiling      <= 0 ;
            count_filter      <= 0 ;
            load_ifm          <= 0 ;
            load_wgt          <= 0 ;
            ifm_demux         <= 0 ;
            ifm_mux           <= 1 ;
            ifm_RF_shift_en_1 <= 0 ;
            ifm_RF_shift_en_2 <= 0 ;
            wgt_RF_shift_en   <= 0 ;
            select_wgt        <= 1 ;
            reset_pe          <= 0 ;
            write_out_en      <= 0 ;
        end
        else begin
            case (next_state)
                IDLE: begin
                    count_load        <= 0 ;
                    count_compute_1   <= 0 ;
                    count_compute_2   <= 0 ;
                    count_write       <= 0 ;
                    count_tiling      <= 0 ;
                    count_filter      <= 0 ;
                    load_ifm          <= 0 ;
                    load_wgt          <= 0 ;
                    ifm_demux         <= 0 ;
                    ifm_mux           <= 1 ;
                    ifm_RF_shift_en_1 <= 0 ;
                    ifm_RF_shift_en_2 <= 0 ;
                    wgt_RF_shift_en   <= 0 ;
                    select_wgt        <= 1 ;
                    reset_pe          <= 0 ;
                    write_out_en      <= 0 ;
                end 
                LOAD_WEIGHT: begin
                    count_write <= 0;

                    count_load   <= count_load + 1;
                    count_tiling <= (count_load == NO_CYCLE_LOAD - 1) ? count_tiling + 1 : count_tiling;
                    count_filter <= (count_load == NO_CYCLE_LOAD - 1) ? count_filter + 1 : count_filter;
                    
                    load_ifm          <= 1 ;
                    load_wgt          <= 1 ;
                    ifm_demux         <= 0 ;
                    ifm_mux           <= 1 ;
                    ifm_RF_shift_en_1 <= 1 ;
                    ifm_RF_shift_en_2 <= 0 ;
                    wgt_RF_shift_en   <= {SYSTOLIC_SIZE{1'b1}};
                    select_wgt        <= 1 ;
                    reset_pe          <= 0 ;
                    write_out_en      <= 0 ;
                end
                LOAD_COMPUTE: begin
                    count_load <= 0;

                    count_compute_1 <= count_compute_1 + 1;
                    count_tiling    <= (count_compute_1 == NO_CYCLE_COMPUTE - 1) ? count_tiling + 1 : count_tiling;

                    load_ifm          <= (count_compute_1 < NO_CYCLE_LOAD) ? 1 : 0;
                    load_wgt          <= 0 ;
                    ifm_demux         <= 1 ;
                    ifm_mux           <= 0 ;
                    ifm_RF_shift_en_1 <= 1 ;
                    ifm_RF_shift_en_2 <= (count_compute_1 < NO_CYCLE_LOAD) ? 1 : 0;

                    for (i = 0; i < SYSTOLIC_SIZE; i = i + 1) begin
                        wgt_RF_shift_en[i] <= (count_compute_1 >= i && count_compute_1 < NO_CYCLE_LOAD + i) ? 1 : 0 ;
                    end
                    
                    select_wgt   <= 0;
                    reset_pe     <= (count_compute_1 == NO_CYCLE_COMPUTE - 2) ? 1 : 0;
                    write_out_en <= (count_compute_1 == NO_CYCLE_COMPUTE - 1) ? 1 : 0;
                end
                LOAD_COMPUTE_WRITE: begin
                    count_compute_1 <= 0;

                    count_compute_2 <= (count_compute_2 == NO_CYCLE_COMPUTE) ? 0 : count_compute_2 + 1;
                    count_tiling    <= (count_compute_2 == NO_CYCLE_COMPUTE - 1) ? count_tiling + 1 : count_tiling;

                    load_ifm          <= (count_compute_2 < NO_CYCLE_LOAD) ? 1 : 0;
                    load_wgt          <= 0;
                    ifm_demux         <= (count_compute_2 == 0) ? ~ifm_demux : ifm_demux;
                    ifm_mux           <= (count_compute_2 == 0) ? ~ifm_mux   : ifm_mux;
                    ifm_RF_shift_en_1 <= (ifm_demux == 0) ? ((count_compute_2 < NO_CYCLE_LOAD) ? 1 : 0) : 1;
                    ifm_RF_shift_en_2 <= (ifm_demux == 1) ? ((count_compute_2 < NO_CYCLE_LOAD) ? 1 : 0) : 1;

                    for (i = 0; i < SYSTOLIC_SIZE; i = i + 1) begin
                        wgt_RF_shift_en[i] <= (count_compute_2 >= i && count_compute_2 < NO_CYCLE_LOAD + i) ? 1 : 0 ;
                    end

                    select_wgt   <= 0;
                    reset_pe     <= (count_compute_2 == NO_CYCLE_COMPUTE - 2) ? 1 : 0;
                    write_out_en <= (count_compute_2 <= SYSTOLIC_SIZE    - 1) ? 1 : 0;
                end
                COMPUTE_WRITE: begin
                    count_compute_2 <= 0 ;
                    count_tiling    <= 0 ;

                    count_compute_1 <= count_compute_1 + 1;

                    load_ifm          <= 0          ;
                    load_wgt          <= 0          ;
                    ifm_demux         <= (count_compute_1 == 0) ? ~ifm_demux : ifm_demux;
                    ifm_mux           <= (count_compute_1 == 0) ? ~ifm_mux   : ifm_mux;
                    ifm_RF_shift_en_1 <= 1          ;
                    ifm_RF_shift_en_2 <= 1          ;

                    for (i = 0; i < SYSTOLIC_SIZE; i = i + 1) begin
                        wgt_RF_shift_en[i] <= (count_compute_1 >= i && count_compute_1 < NO_CYCLE_LOAD + i) ? 1 : 0 ;
                    end

                    select_wgt   <= 0;
                    reset_pe     <= (count_compute_1 >= NO_CYCLE_COMPUTE - 2) ? 1 : 0;
                    write_out_en <= (count_compute_1 <= SYSTOLIC_SIZE    - 1) ? 1 : 0;
                end
                WRITE: begin
                    count_compute_1 <= 0;
                    count_write     <= count_write + 1;

                    load_ifm          <= 0 ;
                    load_wgt          <= 0 ;
                    ifm_demux         <= 0 ;
                    ifm_mux           <= 1 ;
                    ifm_RF_shift_en_1 <= 0 ;
                    ifm_RF_shift_en_2 <= 0 ;
                    wgt_RF_shift_en   <= 0 ;
                    select_wgt        <= 0 ;
                    reset_pe          <= 1 ;
                    write_out_en      <= 1 ;
                end
            endcase
        end
    end

endmodule

systolic_array_layer0/main_controller_tb.v
module main_controller_tb();

parameter NO_FILTER     = 32 ;
parameter KERNEL_SIZE   = 3  ;
parameter NO_CHANNEL    = 3  ;
parameter SYSTOLIC_SIZE = 16 ;

reg                          clk                                  ;
reg                          rst_n                                ;
reg                          start                                ;
wire                         load_ifm, load_wgt                   ;
wire                         ifm_demux, ifm_mux                   ;
wire                         ifm_RF_shift_en_1, ifm_RF_shift_en_2 ;
wire [SYSTOLIC_SIZE - 1 : 0] wgt_RF_shift_en                      ;
wire                         select_wgt                           ;
wire                         reset_pe                             ;
wire                         write_out_en                         ;

main_controller #(
    .NO_FILTER     ( NO_FILTER     ) ,
    .KERNEL_SIZE   ( KERNEL_SIZE   ) ,
    .NO_CHANNEL    ( NO_CHANNEL    ) ,
    .SYSTOLIC_SIZE ( SYSTOLIC_SIZE )
) main_controller_dut (
    .clk               ( clk               ) ,
    .rst_n             ( rst_n             ) ,
    .start             ( start             ) ,
    .load_ifm          ( load_ifm          ) ,
    .load_wgt          ( load_wgt          ) ,
    .ifm_demux         ( ifm_demux         ) ,
    .ifm_mux           ( ifm_mux           ) ,
    .ifm_RF_shift_en_1 ( ifm_RF_shift_en_1 ) ,
    .ifm_RF_shift_en_2 ( ifm_RF_shift_en_2 ) ,
    .wgt_RF_shift_en   ( wgt_RF_shift_en   ) ,
    .select_wgt        ( select_wgt        ) ,
    .reset_pe          ( reset_pe          ) ,
    .write_out_en      ( write_out_en      )
);

always #5 clk = ~clk;

initial begin
    clk = 0;
    rst_n = 0;
    start = 0;

    #30 rst_n = 1;
    #20 start = 1;
    #5000 $finish;
end

initial begin
    $dumpfile ("main_controller.VCD");
    $dumpvars (0, main_controller_tb);
end

endmodule

systolic_array_layer0/main_controller.VCD
$date
	Sat Mar 22 05:53:59 2025
$end
$version
	Icarus Verilog
$end
$timescale
	1s
$end
$scope module main_controller_tb $end
$var wire 1 ! write_out_en $end
$var wire 16 " wgt_RF_shift_en [15:0] $end
$var wire 1 # select_wgt $end
$var wire 1 $ reset_pe $end
$var wire 1 % load_wgt $end
$var wire 1 & load_ifm $end
$var wire 1 ' ifm_mux $end
$var wire 1 ( ifm_demux $end
$var wire 1 ) ifm_RF_shift_en_2 $end
$var wire 1 * ifm_RF_shift_en_1 $end
$var parameter 32 + KERNEL_SIZE $end
$var parameter 32 , NO_CHANNEL $end
$var parameter 32 - NO_FILTER $end
$var parameter 32 . SYSTOLIC_SIZE $end
$var reg 1 / clk $end
$var reg 1 0 rst_n $end
$var reg 1 1 start $end
$scope module main_controller_dut $end
$var wire 1 / clk $end
$var wire 1 0 rst_n $end
$var wire 1 1 start $end
$var parameter 3 2 COMPUTE_WRITE $end
$var parameter 3 3 IDLE $end
$var parameter 32 4 KERNEL_SIZE $end
$var parameter 3 5 LOAD_COMPUTE $end
$var parameter 3 6 LOAD_COMPUTE_WRITE $end
$var parameter 3 7 LOAD_WEIGHT $end
$var parameter 32 8 NO_CHANNEL $end
$var parameter 98 9 NO_CYCLE_COMPUTE $end
$var parameter 96 : NO_CYCLE_LOAD $end
$var parameter 32 ; NO_FILTER $end
$var parameter 34 < NO_LOAD_FILTER $end
$var parameter 32 = SYSTOLIC_SIZE $end
$var parameter 3 > WRITE $end
$var reg 6 ? count_compute_1 [5:0] $end
$var reg 6 @ count_compute_2 [5:0] $end
$var reg 3 A count_filter [2:0] $end
$var reg 5 B count_load [4:0] $end
$var reg 14 C count_tiling [13:0] $end
$var reg 5 D count_write [4:0] $end
$var reg 3 E current_state [2:0] $end
$var reg 1 * ifm_RF_shift_en_1 $end
$var reg 1 ) ifm_RF_shift_en_2 $end
$var reg 1 ( ifm_demux $end
$var reg 1 ' ifm_mux $end
$var reg 1 & load_ifm $end
$var reg 1 % load_wgt $end
$var reg 3 F next_state [2:0] $end
$var reg 1 $ reset_pe $end
$var reg 1 # select_wgt $end
$var reg 16 G wgt_RF_shift_en [15:0] $end
$var reg 1 ! write_out_en $end
$var integer 32 H i [31:0] $end
$upscope $end
$upscope $end
$enddefinitions $end
$comment Show the parameter values. $end
$dumpall
b101 >
b10000 =
b10 <
b100000 ;
b11011 :
b111010 9
b11 8
b1 7
b11 6
b10 5
b11 4
b0 3
b100 2
b10000 .
b100000 -
b11 ,
b11 +
$end
#0
$dumpvars
bx H
b0 G
b0 F
b0 E
b0 D
b0 C
b0 B
b0 A
b0 @
b0 ?
01
00
0/
0*
0)
0(
1'
0&
0%
0$
1#
b0 "
0!
$end
#5
1/
#10
0/
#15
1/
#20
0/
#25
1/
#30
0/
10
#35
1/
#40
0/
#45
1/
#50
b1 F
0/
11
#55
b1 E
b1111111111111111 "
b1111111111111111 G
1*
1%
1&
b1 B
1/
#60
0/
#65
b10 B
1/
#70
0/
#75
b11 B
1/
#80
0/
#85
b100 B
1/
#90
0/
#95
b101 B
1/
#100
0/
#105
b110 B
1/
#110
0/
#115
b111 B
1/
#120
0/
#125
b1000 B
1/
#130
0/
#135
b1001 B
1/
#140
0/
#145
b1010 B
1/
#150
0/
#155
b1011 B
1/
#160
0/
#165
b1100 B
1/
#170
0/
#175
b1101 B
1/
#180
0/
#185
b1110 B
1/
#190
0/
#195
b1111 B
1/
#200
0/
#205
b10000 B
1/
#210
0/
#215
b10001 B
1/
#220
0/
#225
b10010 B
1/
#230
0/
#235
b10011 B
1/
#240
0/
#245
b10100 B
1/
#250
0/
#255
b10101 B
1/
#260
0/
#265
b10110 B
1/
#270
0/
#275
b10111 B
1/
#280
0/
#285
b11000 B
1/
#290
0/
#295
b11001 B
1/
#300
0/
#305
b11010 B
1/
#310
0/
#315
b10 F
b1 A
b1 C
b11011 B
1/
#320
0/
#325
0#
b1 "
b1 G
1)
0'
1(
0%
b1 ?
b0 B
b10 E
b10000 H
1/
#330
0/
#335
b11 "
b11 G
b10 ?
b10000 H
1/
#340
0/
#345
b111 "
b111 G
b11 ?
b10000 H
1/
#350
0/
#355
b1111 "
b1111 G
b100 ?
b10000 H
1/
#360
0/
#365
b11111 "
b11111 G
b101 ?
b10000 H
1/
#370
0/
#375
b111111 "
b111111 G
b110 ?
b10000 H
1/
#380
0/
#385
b1111111 "
b1111111 G
b111 ?
b10000 H
1/
#390
0/
#395
b11111111 "
b11111111 G
b1000 ?
b10000 H
1/
#400
0/
#405
b111111111 "
b111111111 G
b1001 ?
b10000 H
1/
#410
0/
#415
b1111111111 "
b1111111111 G
b1010 ?
b10000 H
1/
#420
0/
#425
b11111111111 "
b11111111111 G
b1011 ?
b10000 H
1/
#430
0/
#435
b111111111111 "
b111111111111 G
b1100 ?
b10000 H
1/
#440
0/
#445
b1111111111111 "
b1111111111111 G
b1101 ?
b10000 H
1/
#450
0/
#455
b11111111111111 "
b11111111111111 G
b1110 ?
b10000 H
1/
#460
0/
#465
b111111111111111 "
b111111111111111 G
b1111 ?
b10000 H
1/
#470
0/
#475
b1111111111111111 "
b1111111111111111 G
b10000 ?
b10000 H
1/
#480
0/
#485
b10001 ?
b10000 H
1/
#490
0/
#495
b10010 ?
b10000 H
1/
#500
0/
#505
b10011 ?
b10000 H
1/
#510
0/
#515
b10100 ?
b10000 H
1/
#520
0/
#525
b10101 ?
b10000 H
1/
#530
0/
#535
b10110 ?
b10000 H
1/
#540
0/
#545
b10111 ?
b10000 H
1/
#550
0/
#555
b11000 ?
b10000 H
1/
#560
0/
#565
b11001 ?
b10000 H
1/
#570
0/
#575
b11010 ?
b10000 H
1/
#580
0/
#585
b11011 ?
b10000 H
1/
#590
0/
#595
b1111111111111110 "
b1111111111111110 G
0)
0&
b11100 ?
b10000 H
1/
#600
0/
#605
b1111111111111100 "
b1111111111111100 G
b11101 ?
b10000 H
1/
#610
0/
#615
b1111111111111000 "
b1111111111111000 G
b11110 ?
b10000 H
1/
#620
0/
#625
b1111111111110000 "
b1111111111110000 G
b11111 ?
b10000 H
1/
#630
0/
#635
b1111111111100000 "
b1111111111100000 G
b100000 ?
b10000 H
1/
#640
0/
#645
b1111111111000000 "
b1111111111000000 G
b100001 ?
b10000 H
1/
#650
0/
#655
b1111111110000000 "
b1111111110000000 G
b100010 ?
b10000 H
1/
#660
0/
#665
b1111111100000000 "
b1111111100000000 G
b100011 ?
b10000 H
1/
#670
0/
#675
b1111111000000000 "
b1111111000000000 G
b100100 ?
b10000 H
1/
#680
0/
#685
b1111110000000000 "
b1111110000000000 G
b100101 ?
b10000 H
1/
#690
0/
#695
b1111100000000000 "
b1111100000000000 G
b100110 ?
b10000 H
1/
#700
0/
#705
b1111000000000000 "
b1111000000000000 G
b100111 ?
b10000 H
1/
#710
0/
#715
b1110000000000000 "
b1110000000000000 G
b101000 ?
b10000 H
1/
#720
0/
#725
b1100000000000000 "
b1100000000000000 G
b101001 ?
b10000 H
1/
#730
0/
#735
b1000000000000000 "
b1000000000000000 G
b101010 ?
b10000 H
1/
#740
0/
#745
b0 "
b0 G
b101011 ?
b10000 H
1/
#750
0/
#755
b101100 ?
b10000 H
1/
#760
0/
#765
b101101 ?
b10000 H
1/
#770
0/
#775
b101110 ?
b10000 H
1/
#780
0/
#785
b101111 ?
b10000 H
1/
#790
0/
#795
b110000 ?
b10000 H
1/
#800
0/
#805
b110001 ?
b10000 H
1/
#810
0/
#815
b110010 ?
b10000 H
1/
#820
0/
#825
b110011 ?
b10000 H
1/
#830
0/
#835
b110100 ?
b10000 H
1/
#840
0/
#845
b110101 ?
b10000 H
1/
#850
0/
#855
b110110 ?
b10000 H
1/
#860
0/
#865
b110111 ?
b10000 H
1/
#870
0/
#875
b111000 ?
b10000 H
1/
#880
0/
#885
1$
b111001 ?
b10000 H
1/
#890
0/
#895
b11 F
1!
0$
b10 C
b111010 ?
b10000 H
1/
#900
0/
#905
b1 "
b1 G
1)
1'
0(
1&
b1 @
b0 ?
b11 E
b10000 H
1/
#910
0/
#915
b11 "
b11 G
b10 @
b10000 H
1/
#920
0/
#925
b111 "
b111 G
b11 @
b10000 H
1/
#930
0/
#935
b1111 "
b1111 G
b100 @
b10000 H
1/
#940
0/
#945
b11111 "
b11111 G
b101 @
b10000 H
1/
#950
0/
#955
b111111 "
b111111 G
b110 @
b10000 H
1/
#960
0/
#965
b1111111 "
b1111111 G
b111 @
b10000 H
1/
#970
0/
#975
b11111111 "
b11111111 G
b1000 @
b10000 H
1/
#980
0/
#985
b111111111 "
b111111111 G
b1001 @
b10000 H
1/
#990
0/
#995
b1111111111 "
b1111111111 G
b1010 @
b10000 H
1/
#1000
0/
#1005
b11111111111 "
b11111111111 G
b1011 @
b10000 H
1/
#1010
0/
#1015
b111111111111 "
b111111111111 G
b1100 @
b10000 H
1/
#1020
0/
#1025
b1111111111111 "
b1111111111111 G
b1101 @
b10000 H
1/
#1030
0/
#1035
b11111111111111 "
b11111111111111 G
b1110 @
b10000 H
1/
#1040
0/
#1045
b111111111111111 "
b111111111111111 G
b1111 @
b10000 H
1/
#1050
0/
#1055
b1111111111111111 "
b1111111111111111 G
b10000 @
b10000 H
1/
#1060
0/
#1065
0!
b10001 @
b10000 H
1/
#1070
0/
#1075
b10010 @
b10000 H
1/
#1080
0/
#1085
b10011 @
b10000 H
1/
#1090
0/
#1095
b10100 @
b10000 H
1/
#1100
0/
#1105
b10101 @
b10000 H
1/
#1110
0/
#1115
b10110 @
b10000 H
1/
#1120
0/
#1125
b10111 @
b10000 H
1/
#1130
0/
#1135
b11000 @
b10000 H
1/
#1140
0/
#1145
b11001 @
b10000 H
1/
#1150
0/
#1155
b11010 @
b10000 H
1/
#1160
0/
#1165
b11011 @
b10000 H
1/
#1170
0/
#1175
b1111111111111110 "
b1111111111111110 G
0*
0&
b11100 @
b10000 H
1/
#1180
0/
#1185
b1111111111111100 "
b1111111111111100 G
b11101 @
b10000 H
1/
#1190
0/
#1195
b1111111111111000 "
b1111111111111000 G
b11110 @
b10000 H
1/
#1200
0/
#1205
b1111111111110000 "
b1111111111110000 G
b11111 @
b10000 H
1/
#1210
0/
#1215
b1111111111100000 "
b1111111111100000 G
b100000 @
b10000 H
1/
#1220
0/
#1225
b1111111111000000 "
b1111111111000000 G
b100001 @
b10000 H
1/
#1230
0/
#1235
b1111111110000000 "
b1111111110000000 G
b100010 @
b10000 H
1/
#1240
0/
#1245
b1111111100000000 "
b1111111100000000 G
b100011 @
b10000 H
1/
#1250
0/
#1255
b1111111000000000 "
b1111111000000000 G
b100100 @
b10000 H
1/
#1260
0/
#1265
b1111110000000000 "
b1111110000000000 G
b100101 @
b10000 H
1/
#1270
0/
#1275
b1111100000000000 "
b1111100000000000 G
b100110 @
b10000 H
1/
#1280
0/
#1285
b1111000000000000 "
b1111000000000000 G
b100111 @
b10000 H
1/
#1290
0/
#1295
b1110000000000000 "
b1110000000000000 G
b101000 @
b10000 H
1/
#1300
0/
#1305
b1100000000000000 "
b1100000000000000 G
b101001 @
b10000 H
1/
#1310
0/
#1315
b1000000000000000 "
b1000000000000000 G
b101010 @
b10000 H
1/
#1320
0/
#1325
b0 "
b0 G
b101011 @
b10000 H
1/
#1330
0/
#1335
b101100 @
b10000 H
1/
#1340
0/
#1345
b101101 @
b10000 H
1/
#1350
0/
#1355
b101110 @
b10000 H
1/
#1360
0/
#1365
b101111 @
b10000 H
1/
#1370
0/
#1375
b110000 @
b10000 H
1/
#1380
0/
#1385
b110001 @
b10000 H
1/
#1390
0/
#1395
b110010 @
b10000 H
1/
#1400
0/
#1405
b110011 @
b10000 H
1/
#1410
0/
#1415
b110100 @
b10000 H
1/
#1420
0/
#1425
b110101 @
b10000 H
1/
#1430
0/
#1435
b110110 @
b10000 H
1/
#1440
0/
#1445
b110111 @
b10000 H
1/
#1450
0/
#1455
b111000 @
b10000 H
1/
#1460
0/
#1465
1$
b111001 @
b10000 H
1/
#1470
0/
#1475
b100 F
0$
b11 C
b111010 @
b10000 H
1/
#1480
0/
#1485
1!
b1 "
b1 G
1*
0'
1(
b1 ?
b0 C
b0 @
b100 E
b10000 H
1/
#1490
0/
#1495
b11 "
b11 G
b10 ?
b10000 H
1/
#1500
0/
#1505
b111 "
b111 G
b11 ?
b10000 H
1/
#1510
0/
#1515
b1111 "
b1111 G
b100 ?
b10000 H
1/
#1520
0/
#1525
b11111 "
b11111 G
b101 ?
b10000 H
1/
#1530
0/
#1535
b111111 "
b111111 G
b110 ?
b10000 H
1/
#1540
0/
#1545
b1111111 "
b1111111 G
b111 ?
b10000 H
1/
#1550
0/
#1555
b11111111 "
b11111111 G
b1000 ?
b10000 H
1/
#1560
0/
#1565
b111111111 "
b111111111 G
b1001 ?
b10000 H
1/
#1570
0/
#1575
b1111111111 "
b1111111111 G
b1010 ?
b10000 H
1/
#1580
0/
#1585
b11111111111 "
b11111111111 G
b1011 ?
b10000 H
1/
#1590
0/
#1595
b111111111111 "
b111111111111 G
b1100 ?
b10000 H
1/
#1600
0/
#1605
b1111111111111 "
b1111111111111 G
b1101 ?
b10000 H
1/
#1610
0/
#1615
b11111111111111 "
b11111111111111 G
b1110 ?
b10000 H
1/
#1620
0/
#1625
b111111111111111 "
b111111111111111 G
b1111 ?
b10000 H
1/
#1630
0/
#1635
b1111111111111111 "
b1111111111111111 G
b10000 ?
b10000 H
1/
#1640
0/
#1645
0!
b10001 ?
b10000 H
1/
#1650
0/
#1655
b10010 ?
b10000 H
1/
#1660
0/
#1665
b10011 ?
b10000 H
1/
#1670
0/
#1675
b10100 ?
b10000 H
1/
#1680
0/
#1685
b10101 ?
b10000 H
1/
#1690
0/
#1695
b10110 ?
b10000 H
1/
#1700
0/
#1705
b10111 ?
b10000 H
1/
#1710
0/
#1715
b11000 ?
b10000 H
1/
#1720
0/
#1725
b11001 ?
b10000 H
1/
#1730
0/
#1735
b11010 ?
b10000 H
1/
#1740
0/
#1745
b11011 ?
b10000 H
1/
#1750
0/
#1755
b1111111111111110 "
b1111111111111110 G
b11100 ?
b10000 H
1/
#1760
0/
#1765
b1111111111111100 "
b1111111111111100 G
b11101 ?
b10000 H
1/
#1770
0/
#1775
b1111111111111000 "
b1111111111111000 G
b11110 ?
b10000 H
1/
#1780
0/
#1785
b1111111111110000 "
b1111111111110000 G
b11111 ?
b10000 H
1/
#1790
0/
#1795
b1111111111100000 "
b1111111111100000 G
b100000 ?
b10000 H
1/
#1800
0/
#1805
b1111111111000000 "
b1111111111000000 G
b100001 ?
b10000 H
1/
#1810
0/
#1815
b1111111110000000 "
b1111111110000000 G
b100010 ?
b10000 H
1/
#1820
0/
#1825
b1111111100000000 "
b1111111100000000 G
b100011 ?
b10000 H
1/
#1830
0/
#1835
b1111111000000000 "
b1111111000000000 G
b100100 ?
b10000 H
1/
#1840
0/
#1845
b1111110000000000 "
b1111110000000000 G
b100101 ?
b10000 H
1/
#1850
0/
#1855
b1111100000000000 "
b1111100000000000 G
b100110 ?
b10000 H
1/
#1860
0/
#1865
b1111000000000000 "
b1111000000000000 G
b100111 ?
b10000 H
1/
#1870
0/
#1875
b1110000000000000 "
b1110000000000000 G
b101000 ?
b10000 H
1/
#1880
0/
#1885
b1100000000000000 "
b1100000000000000 G
b101001 ?
b10000 H
1/
#1890
0/
#1895
b1000000000000000 "
b1000000000000000 G
b101010 ?
b10000 H
1/
#1900
0/
#1905
b0 "
b0 G
b101011 ?
b10000 H
1/
#1910
0/
#1915
b101100 ?
b10000 H
1/
#1920
0/
#1925
b101101 ?
b10000 H
1/
#1930
0/
#1935
b101110 ?
b10000 H
1/
#1940
0/
#1945
b101111 ?
b10000 H
1/
#1950
0/
#1955
b110000 ?
b10000 H
1/
#1960
0/
#1965
b110001 ?
b10000 H
1/
#1970
0/
#1975
b110010 ?
b10000 H
1/
#1980
0/
#1985
b110011 ?
b10000 H
1/
#1990
0/
#1995
b110100 ?
b10000 H
1/
#2000
0/
#2005
b110101 ?
b10000 H
1/
#2010
0/
#2015
b110110 ?
b10000 H
1/
#2020
0/
#2025
b110111 ?
b10000 H
1/
#2030
0/
#2035
b111000 ?
b10000 H
1/
#2040
0/
#2045
1$
b111001 ?
b10000 H
1/
#2050
0/
#2055
b101 F
b111010 ?
b10000 H
1/
#2060
0/
#2065
1!
0)
0*
1'
0(
b1 D
b0 ?
b101 E
1/
#2070
0/
#2075
b10 D
1/
#2080
0/
#2085
b11 D
1/
#2090
0/
#2095
b100 D
1/
#2100
0/
#2105
b101 D
1/
#2110
0/
#2115
b110 D
1/
#2120
0/
#2125
b111 D
1/
#2130
0/
#2135
b1000 D
1/
#2140
0/
#2145
b1001 D
1/
#2150
0/
#2155
b1010 D
1/
#2160
0/
#2165
b1011 D
1/
#2170
0/
#2175
b1100 D
1/
#2180
0/
#2185
b1101 D
1/
#2190
0/
#2195
b1110 D
1/
#2200
0/
#2205
b1111 D
1/
#2210
0/
#2215
b1 F
b10000 D
1/
#2220
0/
#2225
0!
0$
1#
b1111111111111111 "
b1111111111111111 G
1*
1%
1&
b1 B
b0 D
b1 E
1/
#2230
0/
#2235
b10 B
1/
#2240
0/
#2245
b11 B
1/
#2250
0/
#2255
b100 B
1/
#2260
0/
#2265
b101 B
1/
#2270
0/
#2275
b110 B
1/
#2280
0/
#2285
b111 B
1/
#2290
0/
#2295
b1000 B
1/
#2300
0/
#2305
b1001 B
1/
#2310
0/
#2315
b1010 B
1/
#2320
0/
#2325
b1011 B
1/
#2330
0/
#2335
b1100 B
1/
#2340
0/
#2345
b1101 B
1/
#2350
0/
#2355
b1110 B
1/
#2360
0/
#2365
b1111 B
1/
#2370
0/
#2375
b10000 B
1/
#2380
0/
#2385
b10001 B
1/
#2390
0/
#2395
b10010 B
1/
#2400
0/
#2405
b10011 B
1/
#2410
0/
#2415
b10100 B
1/
#2420
0/
#2425
b10101 B
1/
#2430
0/
#2435
b10110 B
1/
#2440
0/
#2445
b10111 B
1/
#2450
0/
#2455
b11000 B
1/
#2460
0/
#2465
b11001 B
1/
#2470
0/
#2475
b11010 B
1/
#2480
0/
#2485
b10 F
b10 A
b1 C
b11011 B
1/
#2490
0/
#2495
b10 E
0#
b1 "
b1 G
1)
0'
1(
0%
b1 ?
b0 B
b10000 H
1/
#2500
0/
#2505
b11 "
b11 G
b10 ?
b10000 H
1/
#2510
0/
#2515
b111 "
b111 G
b11 ?
b10000 H
1/
#2520
0/
#2525
b1111 "
b1111 G
b100 ?
b10000 H
1/
#2530
0/
#2535
b11111 "
b11111 G
b101 ?
b10000 H
1/
#2540
0/
#2545
b111111 "
b111111 G
b110 ?
b10000 H
1/
#2550
0/
#2555
b1111111 "
b1111111 G
b111 ?
b10000 H
1/
#2560
0/
#2565
b11111111 "
b11111111 G
b1000 ?
b10000 H
1/
#2570
0/
#2575
b111111111 "
b111111111 G
b1001 ?
b10000 H
1/
#2580
0/
#2585
b1111111111 "
b1111111111 G
b1010 ?
b10000 H
1/
#2590
0/
#2595
b11111111111 "
b11111111111 G
b1011 ?
b10000 H
1/
#2600
0/
#2605
b111111111111 "
b111111111111 G
b1100 ?
b10000 H
1/
#2610
0/
#2615
b1111111111111 "
b1111111111111 G
b1101 ?
b10000 H
1/
#2620
0/
#2625
b11111111111111 "
b11111111111111 G
b1110 ?
b10000 H
1/
#2630
0/
#2635
b111111111111111 "
b111111111111111 G
b1111 ?
b10000 H
1/
#2640
0/
#2645
b1111111111111111 "
b1111111111111111 G
b10000 ?
b10000 H
1/
#2650
0/
#2655
b10001 ?
b10000 H
1/
#2660
0/
#2665
b10010 ?
b10000 H
1/
#2670
0/
#2675
b10011 ?
b10000 H
1/
#2680
0/
#2685
b10100 ?
b10000 H
1/
#2690
0/
#2695
b10101 ?
b10000 H
1/
#2700
0/
#2705
b10110 ?
b10000 H
1/
#2710
0/
#2715
b10111 ?
b10000 H
1/
#2720
0/
#2725
b11000 ?
b10000 H
1/
#2730
0/
#2735
b11001 ?
b10000 H
1/
#2740
0/
#2745
b11010 ?
b10000 H
1/
#2750
0/
