systolic_array_layer0/ofm_addr_controller.v
module ofm_addr_controller #(
    parameter SYSTOLIC_SIZE = 16  ,
    parameter OFM_SIZE      = 414 ,
    parameter ADDR_WIDTH    = 22 

) (
    input                           clk       ,
    input                           rst_n     ,
    input                           write     ,
    output reg [ADDR_WIDTH - 1 : 0] ofm_addr  ,
    output reg                      addr_valid
);

    parameter IDLE             = 2'b00 ;
    parameter NEXT_CHANNEL     = 2'b01 ;
    parameter UPDATE_BASE_ADDR = 2'b10 ;

    reg [2:0] current_state, next_state;
    
    reg [ADDR_WIDTH - 1 : 0] base_addr;

    reg [4:0] count_channel;

    always @(posedge clk or negedge rst_n) begin
        if (!rst_n) current_state <= IDLE;
        else        current_state <= next_state;
    end

    always @(*) begin
        case (current_state)
            IDLE:         if (write)                          next_state = NEXT_CHANNEL;
            NEXT_CHANNEL: if (count_channel == SYSTOLIC_SIZE) next_state = UPDATE_BASE_ADDR;
            UPDATE_BASE_ADDR: next_state = IDLE; 
            default:          next_state = IDLE;
        endcase
    end

    always @(posedge clk or negedge rst_n) begin
        if (!rst_n) begin
            count_channel <= 0 ;
            base_addr     <= 0 ;
            ofm_addr      <= 0 ;
            addr_valid    <= 0 ;
        end
        else begin
            case (next_state)
                IDLE: begin
                    count_channel <= 0         ;
                    ofm_addr      <= base_addr ;
                    addr_valid    <= 0         ;
                end
                NEXT_CHANNEL: begin
                    count_channel <= count_channel + 1 ;
                    ofm_addr      <= base_addr + count_channel * OFM_SIZE * OFM_SIZE ; 
                    addr_valid    <= 1 ;
                end
                UPDATE_BASE_ADDR: begin
                    base_addr  <= base_addr + 16;  
                    addr_valid <= 0;
                end
            endcase
        end
    end

endmodule

systolic_array_layer0/ofm_addr_controller_tb.v
module ofm_addr_controller_tb();

parameter ADDR_WIDTH    = 22  ;
parameter SYSTOLIC_SIZE = 16  ;
parameter OFM_SIZE      = 416 ;

reg                       clk        ;
reg                       rst_n      ;
reg                       write      ;
wire [ADDR_WIDTH - 1 : 0] ofm_addr   ;
wire                      addr_valid ;

ofm_addr_controller #(
    .ADDR_WIDTH    ( ADDR_WIDTH    ) ,
    .SYSTOLIC_SIZE ( SYSTOLIC_SIZE ) ,
    .OFM_SIZE      ( OFM_SIZE      )
) ofm_addr_dut (
    .clk        ( clk        ) ,
    .rst_n      ( rst_n      ) ,
    .write      ( write      ) ,
    .ofm_addr   ( ofm_addr   ) ,
    .addr_valid ( addr_valid )
);

always #5 clk = ~clk;

initial begin
    clk = 0;
    rst_n = 0;
    write = 0;

    #30 rst_n = 1; 
    #50 write = 1;
    #500 write = 0;
    #100 write = 1;
    #500 $finish;
end

initial begin
    $dumpfile ("ofm_addr_controller.VCD");
    $dumpvars (0, ofm_addr_controller_tb);
end

endmodule

systolic_array_layer0/ofm_addr_controller.VCD
$date
	Sat Mar 22 06:43:47 2025
$end
$version
	Icarus Verilog
$end
$timescale
	1s
$end
$scope module ofm_addr_controller_tb $end
$var wire 22 ! ofm_addr [21:0] $end
$var wire 1 " addr_valid $end
$var parameter 32 # ADDR_WIDTH $end
$var parameter 32 $ OFM_SIZE $end
$var parameter 32 % SYSTOLIC_SIZE $end
$var reg 1 & clk $end
$var reg 1 ' rst_n $end
$var reg 1 ( write $end
$scope module ofm_addr_dut $end
$var wire 1 & clk $end
$var wire 1 ' rst_n $end
$var wire 1 ( write $end
$var parameter 32 ) ADDR_WIDTH $end
$var parameter 2 * IDLE $end
$var parameter 2 + NEXT_CHANNEL $end
$var parameter 32 , OFM_SIZE $end
$var parameter 32 - SYSTOLIC_SIZE $end
$var parameter 2 . UPDATE_BASE_ADDR $end
$var reg 1 " addr_valid $end
$var reg 22 / base_addr [21:0] $end
$var reg 5 0 count_channel [4:0] $end
$var reg 3 1 current_state [2:0] $end
$var reg 3 2 next_state [2:0] $end
$var reg 22 3 ofm_addr [21:0] $end
$upscope $end
$upscope $end
$enddefinitions $end
$comment Show the parameter values. $end
$dumpall
b10 .
b10000 -
b110100000 ,
b1 +
b0 *
b10110 )
b10000 %
b110100000 $
b10110 #
$end
#0
$dumpvars
b0 3
b0 2
b0 1
b0 0
b0 /
0(
0'
0&
0"
b0 !
$end
#5
1&
#10
0&
#15
1&
#20
0&
#25
1&
#30
0&
1'
#35
1&
#40
0&
#45
1&
#50
0&
#55
1&
#60
0&
#65
1&
#70
0&
#75
1&
#80
b1 2
0&
1(
#85
1"
b1 0
b1 1
1&
#90
0&
#95
b101010010000000000 !
b101010010000000000 3
b10 0
1&
#100
0&
#105
b1010100100000000000 !
b1010100100000000000 3
b11 0
1&
#110
0&
#115
b1111110110000000000 !
b1111110110000000000 3
b100 0
1&
#120
0&
#125
b10101001000000000000 !
b10101001000000000000 3
b101 0
1&
#130
0&
#135
b11010011010000000000 !
b11010011010000000000 3
b110 0
1&
#140
0&
#145
b11111101100000000000 !
b11111101100000000000 3
b111 0
1&
#150
0&
#155
b100100111110000000000 !
b100100111110000000000 3
b1000 0
1&
#160
0&
#165
b101010010000000000000 !
b101010010000000000000 3
b1001 0
1&
#170
0&
#175
b101111100010000000000 !
b101111100010000000000 3
b1010 0
1&
#180
0&
#185
b110100110100000000000 !
b110100110100000000000 3
b1011 0
1&
#190
0&
#195
b111010000110000000000 !
b111010000110000000000 3
b1100 0
1&
#200
0&
#205
b111111011000000000000 !
b111111011000000000000 3
b1101 0
1&
#210
0&
#215
b1000100101010000000000 !
b1000100101010000000000 3
b1110 0
1&
#220
0&
#225
b1001001111100000000000 !
b1001001111100000000000 3
b1111 0
1&
#230
0&
#235
b10 2
b1001111001110000000000 !
b1001111001110000000000 3
b10000 0
1&
#240
0&
#245
b0 2
0"
b10000 /
b10 1
1&
#250
0&
#255
b1 2
b0 1
b10000 !
b10000 3
b0 0
1&
#260
0&
#265
1"
b1 0
b1 1
1&
#270
0&
#275
b101010010000010000 !
b101010010000010000 3
b10 0
1&
#280
0&
#285
b1010100100000010000 !
b1010100100000010000 3
b11 0
1&
#290
0&
#295
b1111110110000010000 !
b1111110110000010000 3
b100 0
1&
#300
0&
#305
b10101001000000010000 !
b10101001000000010000 3
b101 0
1&
#310
0&
#315
b11010011010000010000 !
b11010011010000010000 3
b110 0
1&
#320
0&
#325
b11111101100000010000 !
b11111101100000010000 3
b111 0
1&
#330
0&
#335
b100100111110000010000 !
b100100111110000010000 3
b1000 0
1&
#340
0&
#345
b101010010000000010000 !
b101010010000000010000 3
b1001 0
1&
#350
0&
#355
b101111100010000010000 !
b101111100010000010000 3
b1010 0
1&
#360
0&
#365
b110100110100000010000 !
b110100110100000010000 3
b1011 0
1&
#370
0&
#375
b111010000110000010000 !
b111010000110000010000 3
b1100 0
1&
#380
0&
#385
b111111011000000010000 !
b111111011000000010000 3
b1101 0
1&
#390
0&
#395
b1000100101010000010000 !
b1000100101010000010000 3
b1110 0
1&
#400
0&
#405
b1001001111100000010000 !
b1001001111100000010000 3
b1111 0
1&
#410
0&
#415
b10 2
b1001111001110000010000 !
b1001111001110000010000 3
b10000 0
1&
#420
0&
#425
b0 2
0"
b100000 /
b10 1
1&
#430
0&
#435
b1 2
b0 1
b100000 !
b100000 3
b0 0
1&
#440
0&
#445
1"
b1 0
b1 1
1&
#450
0&
#455
b101010010000100000 !
b101010010000100000 3
b10 0
1&
#460
0&
#465
b1010100100000100000 !
b1010100100000100000 3
b11 0
1&
#470
0&
#475
b1111110110000100000 !
b1111110110000100000 3
b100 0
1&
#480
0&
#485
b10101001000000100000 !
b10101001000000100000 3
b101 0
1&
#490
0&
#495
b11010011010000100000 !
b11010011010000100000 3
b110 0
1&
#500
0&
#505
b11111101100000100000 !
b11111101100000100000 3
b111 0
1&
#510
0&
#515
b100100111110000100000 !
b100100111110000100000 3
b1000 0
1&
#520
0&
#525
b101010010000000100000 !
b101010010000000100000 3
b1001 0
1&
#530
0&
#535
b101111100010000100000 !
b101111100010000100000 3
b1010 0
1&
#540
0&
#545
b110100110100000100000 !
b110100110100000100000 3
b1011 0
1&
#550
0&
#555
b111010000110000100000 !
b111010000110000100000 3
b1100 0
1&
#560
0&
#565
b111111011000000100000 !
b111111011000000100000 3
b1101 0
1&
#570
0&
#575
b1000100101010000100000 !
b1000100101010000100000 3
b1110 0
1&
#580
0&
0(
#585
b1001001111100000100000 !
b1001001111100000100000 3
b1111 0
1&
#590
0&
#595
b10 2
b1001111001110000100000 !
b1001111001110000100000 3
b10000 0
1&
#600
0&
#605
b0 2
0"
b110000 /
b10 1
1&
#610
0&
#615
b0 1
b110000 !
b110000 3
b0 0
1&
#620
0&
#625
1&
#630
0&
#635
1&
#640
0&
#645
1&
#650
0&
#655
1&
#660
0&
#665
1&
#670
0&
#675
1&
#680
b1 2
0&
1(
#685
1"
b1 0
b1 1
1&
#690
0&
#695
b101010010000110000 !
b101010010000110000 3
b10 0
1&
#700
0&
#705
b1010100100000110000 !
b1010100100000110000 3
b11 0
1&
#710
0&
#715
b1111110110000110000 !
b1111110110000110000 3
b100 0
1&
#720
0&
#725
b10101001000000110000 !
b10101001000000110000 3
b101 0
1&
#730
0&
#735
b11010011010000110000 !
b11010011010000110000 3
b110 0
1&
#740
0&
#745
b11111101100000110000 !
b11111101100000110000 3
b111 0
1&
#750
0&
#755
b100100111110000110000 !
b100100111110000110000 3
b1000 0
1&
#760
0&
#765
b101010010000000110000 !
b101010010000000110000 3
b1001 0
1&
#770
0&
#775
b101111100010000110000 !
b101111100010000110000 3
b1010 0
1&
#780
0&
#785
b110100110100000110000 !
b110100110100000110000 3
b1011 0
1&
#790
0&
#795
b111010000110000110000 !
b111010000110000110000 3
b1100 0
1&
#800
0&
#805
b111111011000000110000 !
b111111011000000110000 3
b1101 0
1&
#810
0&
#815
b1000100101010000110000 !
b1000100101010000110000 3
b1110 0
1&
#820
0&
#825
b1001001111100000110000 !
b1001001111100000110000 3
b1111 0
1&
#830
0&
#835
b10 2
b1001111001110000110000 !
b1001111001110000110000 3
b10000 0
1&
#840
0&
#845
b0 2
0"
b1000000 /
b10 1
1&
#850
0&
#855
b1 2
b0 1
b1000000 !
b1000000 3
b0 0
1&
#860
0&
#865
1"
b1 0
b1 1
1&
#870
0&
#875
b101010010001000000 !
b101010010001000000 3
b10 0
1&
#880
0&
#885
b1010100100001000000 !
b1010100100001000000 3
b11 0
1&
#890
0&
#895
b1111110110001000000 !
b1111110110001000000 3
b100 0
1&
#900
0&
#905
b10101001000001000000 !
b10101001000001000000 3
b101 0
1&
#910
0&
#915
b11010011010001000000 !
b11010011010001000000 3
b110 0
1&
#920
0&
#925
b11111101100001000000 !
b11111101100001000000 3
b111 0
1&
#930
0&
#935
b100100111110001000000 !
b100100111110001000000 3
b1000 0
1&
#940
0&
#945
b101010010000001000000 !
b101010010000001000000 3
b1001 0
1&
#950
0&
#955
b101111100010001000000 !
b101111100010001000000 3
b1010 0
1&
#960
0&
#965
b110100110100001000000 !
b110100110100001000000 3
b1011 0
1&
#970
0&
#975
b111010000110001000000 !
b111010000110001000000 3
b1100 0
1&
#980
0&
#985
b111111011000001000000 !
b111111011000001000000 3
b1101 0
1&
#990
0&
#995
b1000100101010001000000 !
b1000100101010001000000 3
b1110 0
1&
#1000
0&
#1005
b1001001111100001000000 !
b1001001111100001000000 3
b1111 0
1&
#1010
0&
#1015
b10 2
b1001111001110001000000 !
b1001111001110001000000 3
b10000 0
1&
#1020
0&
#1025
b0 2
0"
b1010000 /
b10 1
1&
#1030
0&
#1035
b1 2
b0 1
b1010000 !
b1010000 3
b0 0
1&
#1040
0&
#1045
1"
b1 0
b1 1
1&
#1050
0&
#1055
b101010010001010000 !
b101010010001010000 3
b10 0
1&
#1060
0&
#1065
b1010100100001010000 !
b1010100100001010000 3
b11 0
1&
#1070
0&
#1075
b1111110110001010000 !
b1111110110001010000 3
b100 0
1&
#1080
0&
#1085
b10101001000001010000 !
b10101001000001010000 3
b101 0
1&
#1090
0&
#1095
b11010011010001010000 !
b11010011010001010000 3
b110 0
1&
#1100
0&
#1105
b11111101100001010000 !
b11111101100001010000 3
b111 0
1&
#1110
0&
#1115
b100100111110001010000 !
b100100111110001010000 3
b1000 0
1&
#1120
0&
#1125
b101010010000001010000 !
b101010010000001010000 3
b1001 0
1&
#1130
0&
#1135
b101111100010001010000 !
b101111100010001010000 3
b1010 0
1&
#1140
0&
#1145
b110100110100001010000 !
b110100110100001010000 3
b1011 0
1&
#1150
0&
#1155
b111010000110001010000 !
b111010000110001010000 3
b1100 0
1&
#1160
0&
#1165
b111111011000001010000 !
b111111011000001010000 3
b1101 0
1&
#1170
0&
#1175
b1000100101010001010000 !
b1000100101010001010000 3
b1110 0
1&
