systolic_array_32x32x3_16filters_read_vertically/wgt_shift_RF.v
module wgt_shift_RF #(
	parameter DATA_WIDTH  = 8 , 
	parameter BUFFER_SIZE = 27
) (
	input                           clk             ,
	input                           rst_n           ,
	input                           select_wgt      ,
	input                           wgt_RF_shift_en ,
	input      [DATA_WIDTH - 1 : 0] data_in         ,
	output reg [DATA_WIDTH - 1 : 0] data_out
);

	reg [DATA_WIDTH - 1 : 0] buffer [0 : BUFFER_SIZE - 1];

	integer i;

	always @(posedge clk or negedge rst_n) begin
		if (!rst_n) begin
			data_out      <= 0;
			for (i = 0; i < BUFFER_SIZE; i = i + 1) begin
				buffer[i] <= 0;
			end
		end
		else if (wgt_RF_shift_en) begin
			data_out      <= buffer[BUFFER_SIZE - 1];
			for (i = BUFFER_SIZE - 1; i > 0; i = i - 1) begin
				buffer[i] <= buffer[i - 1];
			end
			buffer[0]     <= (select_wgt) ? data_in : buffer[BUFFER_SIZE - 1];
		end
	end	
	
endmodule

systolic_array_layer0/wgt_shift_RF_tb.v
module wgt_shift_RF_tb();

parameter DATA_WIDTH  = 8  ;
parameter BUFFER_SIZE = 27 ;

reg                       clk             ;
reg                       rst_n           ;
reg                       select_wgt      ;
reg                       wgt_RF_shift_en ;
reg  [DATA_WIDTH - 1 : 0] data_in         ;
wire [DATA_WIDTH - 1 : 0] data_out        ;

wgt_shift_RF #(
    .DATA_WIDTH  ( DATA_WIDTH  ) ,
    .BUFFER_SIZE ( BUFFER_SIZE )
) wgt_shift_RF_dut ( 
    .clk             ( clk             ) ,
    .rst_n           ( rst_n           ) ,
    .select_wgt      ( select_wgt      ) ,
    .wgt_RF_shift_en ( wgt_RF_shift_en ) ,
    .data_in         ( data_in         ) ,
    .data_out        ( data_out        )
);

always #5 clk = ~clk;

integer i;

initial begin
    clk = 0;
    rst_n = 0;
    select_wgt = 1;
    wgt_RF_shift_en = 1;
    data_in = 1;

    #30 rst_n = 1; 
    
    for (i = 2; i < 29; i = i + 1) begin
        data_in = i;
        #10;
    end
    
    #50
    wgt_RF_shift_en = 0;

    for (i = 30; i < 33; i = i + 1) begin
        data_in = i;
        #10;
    end

    #50
    wgt_RF_shift_en = 1;
    select_wgt = 0;

    #10
    
    for (i = 40; i < 33; i = i + 1) begin
        data_in = i;
        #10;
    end

    #500 $finish;
end

initial begin
    $dumpfile ("wgt_shift_RF.VCD");
    $dumpvars (0, wgt_shift_RF_tb);
    $dumpvars (0, wgt_shift_RF_dut.buffer[0]);
    $dumpvars (0, wgt_shift_RF_dut.buffer[1]);
    $dumpvars (0, wgt_shift_RF_dut.buffer[2]);
    $dumpvars (0, wgt_shift_RF_dut.buffer[3]);
    $dumpvars (0, wgt_shift_RF_dut.buffer[4]);
    $dumpvars (0, wgt_shift_RF_dut.buffer[5]);
    $dumpvars (0, wgt_shift_RF_dut.buffer[6]);
    $dumpvars (0, wgt_shift_RF_dut.buffer[7]);
    $dumpvars (0, wgt_shift_RF_dut.buffer[8]);
    $dumpvars (0, wgt_shift_RF_dut.buffer[9]);
    $dumpvars (0, wgt_shift_RF_dut.buffer[10]);
    $dumpvars (0, wgt_shift_RF_dut.buffer[11]);
    $dumpvars (0, wgt_shift_RF_dut.buffer[12]);
    $dumpvars (0, wgt_shift_RF_dut.buffer[13]);
    $dumpvars (0, wgt_shift_RF_dut.buffer[14]);
    $dumpvars (0, wgt_shift_RF_dut.buffer[15]);
    $dumpvars (0, wgt_shift_RF_dut.buffer[16]);
    $dumpvars (0, wgt_shift_RF_dut.buffer[17]);
    $dumpvars (0, wgt_shift_RF_dut.buffer[18]);
    $dumpvars (0, wgt_shift_RF_dut.buffer[19]);
    $dumpvars (0, wgt_shift_RF_dut.buffer[20]);
    $dumpvars (0, wgt_shift_RF_dut.buffer[21]);
    $dumpvars (0, wgt_shift_RF_dut.buffer[22]);
    $dumpvars (0, wgt_shift_RF_dut.buffer[23]);
    $dumpvars (0, wgt_shift_RF_dut.buffer[24]);
    $dumpvars (0, wgt_shift_RF_dut.buffer[25]);
    $dumpvars (0, wgt_shift_RF_dut.buffer[26]);
end

endmodule

systolic_array_layer0/wgt_shift_RF.VCD
$date
	Sat Mar 22 00:20:07 2025
$end
$version
	Icarus Verilog
$end
$timescale
	1s
$end
$scope module wgt_shift_RF_tb $end
$var wire 8 ! data_out [7:0] $end
$var parameter 32 " BUFFER_SIZE $end
$var parameter 32 # DATA_WIDTH $end
$var reg 1 $ clk $end
$var reg 8 % data_in [7:0] $end
$var reg 1 & rst_n $end
$var reg 1 ' select_wgt $end
$var reg 1 ( wgt_RF_shift_en $end
$var integer 32 ) i [31:0] $end
$scope module wgt_shift_RF_dut $end
$var wire 1 $ clk $end
$var wire 8 * data_in [7:0] $end
$var wire 1 & rst_n $end
$var wire 1 ' select_wgt $end
$var wire 1 ( wgt_RF_shift_en $end
$var parameter 32 + BUFFER_SIZE $end
$var parameter 32 , DATA_WIDTH $end
$var reg 8 - data_out [7:0] $end
$var integer 32 . i [31:0] $end
$upscope $end
$upscope $end
$scope module wgt_shift_RF_tb $end
$scope module wgt_shift_RF_dut $end
$var reg 8 / \buffer[0] [7:0] $end
$upscope $end
$upscope $end
$scope module wgt_shift_RF_tb $end
$scope module wgt_shift_RF_dut $end
$var reg 8 0 \buffer[1] [7:0] $end
$upscope $end
$upscope $end
$scope module wgt_shift_RF_tb $end
$scope module wgt_shift_RF_dut $end
$var reg 8 1 \buffer[2] [7:0] $end
$upscope $end
$upscope $end
$scope module wgt_shift_RF_tb $end
$scope module wgt_shift_RF_dut $end
$var reg 8 2 \buffer[3] [7:0] $end
$upscope $end
$upscope $end
$scope module wgt_shift_RF_tb $end
$scope module wgt_shift_RF_dut $end
$var reg 8 3 \buffer[4] [7:0] $end
$upscope $end
$upscope $end
$scope module wgt_shift_RF_tb $end
$scope module wgt_shift_RF_dut $end
$var reg 8 4 \buffer[5] [7:0] $end
$upscope $end
$upscope $end
$scope module wgt_shift_RF_tb $end
$scope module wgt_shift_RF_dut $end
$var reg 8 5 \buffer[6] [7:0] $end
$upscope $end
$upscope $end
$scope module wgt_shift_RF_tb $end
$scope module wgt_shift_RF_dut $end
$var reg 8 6 \buffer[7] [7:0] $end
$upscope $end
$upscope $end
$scope module wgt_shift_RF_tb $end
$scope module wgt_shift_RF_dut $end
$var reg 8 7 \buffer[8] [7:0] $end
$upscope $end
$upscope $end
$scope module wgt_shift_RF_tb $end
$scope module wgt_shift_RF_dut $end
$var reg 8 8 \buffer[9] [7:0] $end
$upscope $end
$upscope $end
$scope module wgt_shift_RF_tb $end
$scope module wgt_shift_RF_dut $end
$var reg 8 9 \buffer[10] [7:0] $end
$upscope $end
$upscope $end
$scope module wgt_shift_RF_tb $end
$scope module wgt_shift_RF_dut $end
$var reg 8 : \buffer[11] [7:0] $end
$upscope $end
$upscope $end
$scope module wgt_shift_RF_tb $end
$scope module wgt_shift_RF_dut $end
$var reg 8 ; \buffer[12] [7:0] $end
$upscope $end
$upscope $end
$scope module wgt_shift_RF_tb $end
$scope module wgt_shift_RF_dut $end
$var reg 8 < \buffer[13] [7:0] $end
$upscope $end
$upscope $end
$scope module wgt_shift_RF_tb $end
$scope module wgt_shift_RF_dut $end
$var reg 8 = \buffer[14] [7:0] $end
$upscope $end
$upscope $end
$scope module wgt_shift_RF_tb $end
$scope module wgt_shift_RF_dut $end
$var reg 8 > \buffer[15] [7:0] $end
$upscope $end
$upscope $end
$scope module wgt_shift_RF_tb $end
$scope module wgt_shift_RF_dut $end
$var reg 8 ? \buffer[16] [7:0] $end
$upscope $end
$upscope $end
$scope module wgt_shift_RF_tb $end
$scope module wgt_shift_RF_dut $end
$var reg 8 @ \buffer[17] [7:0] $end
$upscope $end
$upscope $end
$scope module wgt_shift_RF_tb $end
$scope module wgt_shift_RF_dut $end
$var reg 8 A \buffer[18] [7:0] $end
$upscope $end
$upscope $end
$scope module wgt_shift_RF_tb $end
$scope module wgt_shift_RF_dut $end
$var reg 8 B \buffer[19] [7:0] $end
$upscope $end
$upscope $end
$scope module wgt_shift_RF_tb $end
$scope module wgt_shift_RF_dut $end
$var reg 8 C \buffer[20] [7:0] $end
$upscope $end
$upscope $end
$scope module wgt_shift_RF_tb $end
$scope module wgt_shift_RF_dut $end
$var reg 8 D \buffer[21] [7:0] $end
$upscope $end
$upscope $end
$scope module wgt_shift_RF_tb $end
$scope module wgt_shift_RF_dut $end
$var reg 8 E \buffer[22] [7:0] $end
$upscope $end
$upscope $end
$scope module wgt_shift_RF_tb $end
$scope module wgt_shift_RF_dut $end
$var reg 8 F \buffer[23] [7:0] $end
$upscope $end
$upscope $end
$scope module wgt_shift_RF_tb $end
$scope module wgt_shift_RF_dut $end
$var reg 8 G \buffer[24] [7:0] $end
$upscope $end
$upscope $end
$scope module wgt_shift_RF_tb $end
$scope module wgt_shift_RF_dut $end
$var reg 8 H \buffer[25] [7:0] $end
$upscope $end
$upscope $end
$scope module wgt_shift_RF_tb $end
$scope module wgt_shift_RF_dut $end
$var reg 8 I \buffer[26] [7:0] $end
$upscope $end
$upscope $end
$enddefinitions $end
$comment Show the parameter values. $end
$dumpall
b1000 ,
b11011 +
b1000 #
b11011 "
$end
#0
$dumpvars
b0 I
b0 H
b0 G
b0 F
b0 E
b0 D
b0 C
b0 B
b0 A
b0 @
b0 ?
b0 >
b0 =
b0 <
b0 ;
b0 :
b0 9
b0 8
b0 7
b0 6
b0 5
b0 4
b0 3
b0 2
b0 1
b0 0
b0 /
b11011 .
b0 -
b1 *
bx )
1(
1'
0&
b1 %
0$
b0 !
$end
#5
b0 I
b0 H
b0 G
b0 F
b0 E
b0 D
b0 C
b0 B
b0 A
b0 @
b0 ?
b0 >
b0 =
b0 <
b0 ;
b0 :
b0 9
b0 8
b0 7
b0 6
b0 5
b0 4
b0 3
b0 2
b0 1
b0 0
b0 /
b11011 .
1$
#10
0$
#15
b0 I
b0 H
b0 G
b0 F
b0 E
b0 D
b0 C
b0 B
b0 A
b0 @
b0 ?
b0 >
b0 =
b0 <
b0 ;
b0 :
b0 9
b0 8
b0 7
b0 6
b0 5
b0 4
b0 3
b0 2
b0 1
b0 0
b0 /
b11011 .
1$
#20
0$
#25
b0 I
b0 H
b0 G
b0 F
b0 E
b0 D
b0 C
b0 B
b0 A
b0 @
b0 ?
b0 >
b0 =
b0 <
b0 ;
b0 :
b0 9
b0 8
b0 7
b0 6
b0 5
b0 4
b0 3
b0 2
b0 1
b0 0
b0 /
b11011 .
1$
#30
0$
b10 %
b10 *
b10 )
1&
#35
b10 /
b0 0
b0 1
b0 2
b0 3
b0 4
b0 5
b0 6
b0 7
b0 8
b0 9
b0 :
b0 ;
b0 <
b0 =
b0 >
b0 ?
b0 @
b0 A
b0 B
b0 C
b0 D
b0 E
b0 F
b0 G
b0 H
b0 I
b0 .
1$
#40
0$
b11 %
b11 *
b11 )
#45
b11 /
b10 0
b0 1
b0 2
b0 3
b0 4
b0 5
b0 6
b0 7
b0 8
b0 9
b0 :
b0 ;
b0 <
b0 =
b0 >
b0 ?
b0 @
b0 A
b0 B
b0 C
b0 D
b0 E
b0 F
b0 G
b0 H
b0 I
b0 .
1$
#50
0$
b100 %
b100 *
b100 )
#55
b100 /
b11 0
b10 1
b0 2
b0 3
b0 4
b0 5
b0 6
b0 7
b0 8
b0 9
b0 :
b0 ;
b0 <
b0 =
b0 >
b0 ?
b0 @
b0 A
b0 B
b0 C
b0 D
b0 E
b0 F
b0 G
b0 H
b0 I
b0 .
1$
#60
0$
b101 %
b101 *
b101 )
#65
b101 /
b100 0
b11 1
b10 2
b0 3
b0 4
b0 5
b0 6
b0 7
b0 8
b0 9
b0 :
b0 ;
b0 <
b0 =
b0 >
b0 ?
b0 @
b0 A
b0 B
b0 C
b0 D
b0 E
b0 F
b0 G
b0 H
b0 I
b0 .
1$
#70
0$
b110 %
b110 *
b110 )
#75
b110 /
b101 0
b100 1
b11 2
b10 3
b0 4
b0 5
b0 6
b0 7
b0 8
b0 9
b0 :
b0 ;
b0 <
b0 =
b0 >
b0 ?
b0 @
b0 A
b0 B
b0 C
b0 D
b0 E
b0 F
b0 G
b0 H
b0 I
b0 .
1$
#80
0$
b111 %
b111 *
b111 )
#85
b111 /
b110 0
b101 1
b100 2
b11 3
b10 4
b0 5
b0 6
b0 7
b0 8
b0 9
b0 :
b0 ;
b0 <
b0 =
b0 >
b0 ?
b0 @
b0 A
b0 B
b0 C
b0 D
b0 E
b0 F
b0 G
b0 H
b0 I
b0 .
1$
#90
0$
b1000 %
b1000 *
b1000 )
#95
b1000 /
b111 0
b110 1
b101 2
b100 3
b11 4
b10 5
b0 6
b0 7
b0 8
b0 9
b0 :
b0 ;
b0 <
b0 =
b0 >
b0 ?
b0 @
b0 A
b0 B
b0 C
b0 D
b0 E
b0 F
b0 G
b0 H
b0 I
b0 .
1$
#100
0$
b1001 %
b1001 *
b1001 )
#105
b1001 /
b1000 0
b111 1
b110 2
b101 3
b100 4
b11 5
b10 6
b0 7
b0 8
b0 9
b0 :
b0 ;
b0 <
b0 =
b0 >
b0 ?
b0 @
b0 A
b0 B
b0 C
b0 D
b0 E
b0 F
b0 G
b0 H
b0 I
b0 .
1$
#110
0$
b1010 %
b1010 *
b1010 )
#115
b1010 /
b1001 0
b1000 1
b111 2
b110 3
b101 4
b100 5
b11 6
b10 7
b0 8
b0 9
b0 :
b0 ;
b0 <
b0 =
b0 >
b0 ?
b0 @
b0 A
b0 B
b0 C
b0 D
b0 E
b0 F
b0 G
b0 H
b0 I
b0 .
1$
#120
0$
b1011 %
b1011 *
b1011 )
#125
b1011 /
b1010 0
b1001 1
b1000 2
b111 3
b110 4
b101 5
b100 6
b11 7
b10 8
b0 9
b0 :
b0 ;
b0 <
b0 =
b0 >
b0 ?
b0 @
b0 A
b0 B
b0 C
b0 D
b0 E
b0 F
b0 G
b0 H
b0 I
b0 .
1$
#130
0$
b1100 %
b1100 *
b1100 )
#135
b1100 /
b1011 0
b1010 1
b1001 2
b1000 3
b111 4
b110 5
b101 6
b100 7
b11 8
b10 9
b0 :
b0 ;
b0 <
b0 =
b0 >
b0 ?
b0 @
b0 A
b0 B
b0 C
b0 D
b0 E
b0 F
b0 G
b0 H
b0 I
b0 .
1$
#140
0$
b1101 %
b1101 *
b1101 )
#145
b1101 /
b1100 0
b1011 1
b1010 2
b1001 3
b1000 4
b111 5
b110 6
b101 7
b100 8
b11 9
b10 :
b0 ;
b0 <
b0 =
b0 >
b0 ?
b0 @
b0 A
b0 B
b0 C
b0 D
b0 E
b0 F
b0 G
b0 H
b0 I
b0 .
1$
#150
0$
b1110 %
b1110 *
b1110 )
#155
b1110 /
b1101 0
b1100 1
b1011 2
b1010 3
b1001 4
b1000 5
b111 6
b110 7
b101 8
b100 9
b11 :
b10 ;
b0 <
b0 =
b0 >
b0 ?
b0 @
b0 A
b0 B
b0 C
b0 D
b0 E
b0 F
b0 G
b0 H
b0 I
b0 .
1$
#160
0$
b1111 %
b1111 *
b1111 )
#165
b1111 /
b1110 0
b1101 1
b1100 2
b1011 3
b1010 4
b1001 5
b1000 6
b111 7
b110 8
b101 9
b100 :
b11 ;
b10 <
b0 =
b0 >
b0 ?
b0 @
b0 A
b0 B
b0 C
b0 D
b0 E
b0 F
b0 G
b0 H
b0 I
b0 .
1$
#170
0$
b10000 %
b10000 *
b10000 )
#175
b10000 /
b1111 0
b1110 1
b1101 2
b1100 3
b1011 4
b1010 5
b1001 6
b1000 7
b111 8
b110 9
b101 :
b100 ;
b11 <
b10 =
b0 >
b0 ?
b0 @
b0 A
b0 B
b0 C
b0 D
b0 E
b0 F
b0 G
b0 H
b0 I
b0 .
1$
#180
0$
b10001 %
b10001 *
b10001 )
#185
b10001 /
b10000 0
b1111 1
b1110 2
b1101 3
b1100 4
b1011 5
b1010 6
b1001 7
b1000 8
b111 9
b110 :
b101 ;
b100 <
b11 =
b10 >
b0 ?
b0 @
b0 A
b0 B
b0 C
b0 D
b0 E
b0 F
b0 G
b0 H
b0 I
b0 .
1$
#190
0$
b10010 %
b10010 *
b10010 )
#195
b10010 /
b10001 0
b10000 1
b1111 2
b1110 3
b1101 4
b1100 5
b1011 6
b1010 7
b1001 8
b1000 9
b111 :
b110 ;
b101 <
b100 =
b11 >
b10 ?
b0 @
b0 A
b0 B
b0 C
b0 D
b0 E
b0 F
b0 G
b0 H
b0 I
b0 .
1$
#200
0$
b10011 %
b10011 *
b10011 )
#205
b10011 /
b10010 0
b10001 1
b10000 2
b1111 3
b1110 4
b1101 5
b1100 6
b1011 7
b1010 8
b1001 9
b1000 :
b111 ;
b110 <
b101 =
b100 >
b11 ?
b10 @
b0 A
b0 B
b0 C
b0 D
b0 E
b0 F
b0 G
b0 H
b0 I
b0 .
1$
#210
0$
b10100 %
b10100 *
b10100 )
#215
b10100 /
b10011 0
b10010 1
b10001 2
b10000 3
b1111 4
b1110 5
b1101 6
b1100 7
b1011 8
b1010 9
b1001 :
b1000 ;
b111 <
b110 =
b101 >
b100 ?
b11 @
b10 A
b0 B
b0 C
b0 D
b0 E
b0 F
b0 G
b0 H
b0 I
b0 .
1$
#220
0$
b10101 %
b10101 *
b10101 )
#225
b10101 /
b10100 0
b10011 1
b10010 2
b10001 3
b10000 4
b1111 5
b1110 6
b1101 7
b1100 8
b1011 9
b1010 :
b1001 ;
b1000 <
b111 =
b110 >
b101 ?
b100 @
b11 A
b10 B
b0 C
b0 D
b0 E
b0 F
b0 G
b0 H
b0 I
b0 .
1$
#230
0$
b10110 %
b10110 *
b10110 )
#235
b10110 /
b10101 0
b10100 1
b10011 2
b10010 3
b10001 4
b10000 5
b1111 6
b1110 7
b1101 8
b1100 9
b1011 :
b1010 ;
b1001 <
b1000 =
b111 >
b110 ?
b101 @
b100 A
b11 B
b10 C
b0 D
b0 E
b0 F
b0 G
b0 H
b0 I
b0 .
1$
#240
0$
b10111 %
b10111 *
b10111 )
#245
b10111 /
b10110 0
b10101 1
b10100 2
b10011 3
b10010 4
b10001 5
b10000 6
b1111 7
b1110 8
b1101 9
b1100 :
b1011 ;
b1010 <
b1001 =
b1000 >
b111 ?
b110 @
b101 A
b100 B
b11 C
b10 D
b0 E
b0 F
b0 G
b0 H
b0 I
b0 .
1$
#250
0$
b11000 %
b11000 *
b11000 )
#255
b11000 /
b10111 0
b10110 1
b10101 2
b10100 3
b10011 4
b10010 5
b10001 6
b10000 7
b1111 8
b1110 9
b1101 :
b1100 ;
b1011 <
b1010 =
b1001 >
b1000 ?
b111 @
b110 A
b101 B
b100 C
b11 D
b10 E
b0 F
b0 G
b0 H
b0 I
b0 .
1$
#260
0$
b11001 %
b11001 *
b11001 )
#265
b11001 /
b11000 0
b10111 1
b10110 2
b10101 3
b10100 4
b10011 5
b10010 6
b10001 7
b10000 8
b1111 9
b1110 :
b1101 ;
b1100 <
b1011 =
b1010 >
b1001 ?
b1000 @
b111 A
b110 B
b101 C
b100 D
b11 E
b10 F
b0 G
b0 H
b0 I
b0 .
1$
#270
0$
b11010 %
b11010 *
b11010 )
#275
b11010 /
b11001 0
b11000 1
b10111 2
b10110 3
b10101 4
b10100 5
b10011 6
b10010 7
b10001 8
b10000 9
b1111 :
b1110 ;
b1101 <
b1100 =
b1011 >
b1010 ?
b1001 @
b1000 A
b111 B
b110 C
b101 D
b100 E
b11 F
b10 G
b0 H
b0 I
b0 .
1$
#280
0$
b11011 %
b11011 *
b11011 )
#285
b11011 /
b11010 0
b11001 1
b11000 2
b10111 3
b10110 4
b10101 5
b10100 6
b10011 7
b10010 8
b10001 9
b10000 :
b1111 ;
b1110 <
b1101 =
b1100 >
b1011 ?
b1010 @
b1001 A
b1000 B
b111 C
b110 D
b101 E
b100 F
b11 G
b10 H
b0 I
b0 .
1$
#290
0$
b11100 %
b11100 *
b11100 )
#295
b11100 /
b11011 0
b11010 1
b11001 2
b11000 3
b10111 4
b10110 5
b10101 6
b10100 7
b10011 8
b10010 9
b10001 :
b10000 ;
b1111 <
b1110 =
b1101 >
b1100 ?
b1011 @
b1010 A
b1001 B
b1000 C
b111 D
b110 E
b101 F
b100 G
b11 H
b10 I
b0 .
1$
#300
0$
b11101 )
#305
b11100 /
b11100 0
b11011 1
b11010 2
b11001 3
b11000 4
b10111 5
b10110 6
b10101 7
b10100 8
b10011 9
b10010 :
b10001 ;
b10000 <
b1111 =
b1110 >
b1101 ?
b1100 @
b1011 A
b1010 B
b1001 C
b1000 D
b111 E
b110 F
b101 G
b100 H
b11 I
b10 !
b10 -
b0 .
1$
#310
0$
#315
b11100 /
b11100 0
b11100 1
b11011 2
b11010 3
b11001 4
b11000 5
b10111 6
b10110 7
b10101 8
b10100 9
b10011 :
b10010 ;
b10001 <
b10000 =
b1111 >
b1110 ?
b1101 @
b1100 A
b1011 B
b1010 C
b1001 D
b1000 E
b111 F
b110 G
b101 H
b100 I
b11 !
b11 -
b0 .
1$
#320
0$
#325
b11100 /
b11100 0
b11100 1
b11100 2
b11011 3
b11010 4
b11001 5
b11000 6
b10111 7
b10110 8
b10101 9
b10100 :
b10011 ;
b10010 <
b10001 =
b10000 >
b1111 ?
b1110 @
b1101 A
b1100 B
b1011 C
b1010 D
b1001 E
b1000 F
b111 G
b110 H
b101 I
b100 !
b100 -
b0 .
1$
#330
0$
#335
b11100 /
b11100 0
b11100 1
b11100 2
b11100 3
b11011 4
b11010 5
b11001 6
b11000 7
b10111 8
b10110 9
b10101 :
b10100 ;
b10011 <
b10010 =
b10001 >
b10000 ?
b1111 @
b1110 A
b1101 B
b1100 C
b1011 D
b1010 E
b1001 F
b1000 G
b111 H
b110 I
b101 !
b101 -
b0 .
1$
#340
0$
#345
b11100 /
b11100 0
b11100 1
b11100 2
b11100 3
b11100 4
b11011 5
b11010 6
b11001 7
b11000 8
b10111 9
b10110 :
b10101 ;
b10100 <
b10011 =
b10010 >
b10001 ?
b10000 @
b1111 A
b1110 B
b1101 C
b1100 D
b1011 E
b1010 F
b1001 G
b1000 H
b111 I
b110 !
b110 -
b0 .
1$
#350
0$
b11110 %
b11110 *
b11110 )
0(
#355
1$
#360
0$
b11111 %
b11111 *
b11111 )
#365
1$
#370
0$
b100000 %
b100000 *
b100000 )
#375
1$
#380
0$
b100001 )
#385
1$
#390
0$
#395
1$
#400
0$
#405
1$
#410
0$
#415
1$
#420
0$
#425
1$
#430
0$
0'
1(
#435
b111 /
b11100 0
b11100 1
b11100 2
b11100 3
b11100 4
b11100 5
b11011 6
b11010 7
b11001 8
b11000 9
b10111 :
b10110 ;
b10101 <
b10100 =
b10011 >
b10010 ?
b10001 @
b10000 A
b1111 B
b1110 C
b1101 D
b1100 E
b1011 F
b1010 G
b1001 H
b1000 I
b111 !
b111 -
b0 .
1$
#440
0$
b101000 )
#445
b1000 /
b111 0
b11100 1
b11100 2
b11100 3
b11100 4
b11100 5
b11100 6
b11011 7
b11010 8
b11001 9
b11000 :
b10111 ;
b10110 <
b10101 =
b10100 >
b10011 ?
b10010 @
b10001 A
b10000 B
b1111 C
b1110 D
b1101 E
b1100 F
b1011 G
b1010 H
b1001 I
b1000 !
b1000 -
b0 .
1$
#450
0$
#455
b1001 /
b1000 0
b111 1
b11100 2
b11100 3
b11100 4
b11100 5
b11100 6
b11100 7
b11011 8
b11010 9
b11001 :
b11000 ;
b10111 <
b10110 =
b10101 >
b10100 ?
b10011 @
b10010 A
b10001 B
b10000 C
b1111 D
b1110 E
b1101 F
b1100 G
b1011 H
b1010 I
b1001 !
b1001 -
b0 .
1$
#460
0$
#465
b1010 /
b1001 0
b1000 1
b111 2
b11100 3
b11100 4
b11100 5
b11100 6
b11100 7
b11100 8
b11011 9
b11010 :
b11001 ;
b11000 <
b10111 =
b10110 >
b10101 ?
b10100 @
b10011 A
b10010 B
b10001 C
b10000 D
b1111 E
b1110 F
b1101 G
b1100 H
b1011 I
b1010 !
b1010 -
b0 .
1$
#470
0$
#475
b1011 /
b1010 0
b1001 1
b1000 2
b111 3
b11100 4
b11100 5
b11100 6
b11100 7
b11100 8
b11100 9
b11011 :
b11010 ;
b11001 <
b11000 =
b10111 >
b10110 ?
b10101 @
b10100 A
b10011 B
b10010 C
b10001 D
b10000 E
b1111 F
b1110 G
b1101 H
b1100 I
b1011 !
b1011 -
b0 .
1$
#480
0$
#485
b1100 /
b1011 0
b1010 1
b1001 2
b1000 3
b111 4
b11100 5
b11100 6
b11100 7
b11100 8
b11100 9
b11100 :
b11011 ;
b11010 <
b11001 =
b11000 >
b10111 ?
b10110 @
b10101 A
b10100 B
b10011 C
b10010 D
b10001 E
b10000 F
b1111 G
b1110 H
b1101 I
b1100 !
b1100 -
b0 .
1$
#490
0$
#495
b1101 /
b1100 0
b1011 1
b1010 2
b1001 3
b1000 4
b111 5
b11100 6
b11100 7
b11100 8
b11100 9
b11100 :
b11100 ;
b11011 <
b11010 =
b11001 >
b11000 ?
b10111 @
b10110 A
b10101 B
b10100 C
b10011 D
b10010 E
b10001 F
b10000 G
b1111 H
b1110 I
b1101 !
b1101 -
b0 .
1$
#500
0$
#505
b1110 /
b1101 0
b1100 1
b1011 2
b1010 3
b1001 4
b1000 5
b111 6
b11100 7
b11100 8
b11100 9
b11100 :
b11100 ;
b11100 <
b11011 =
b11010 >
b11001 ?
b11000 @
b10111 A
b10110 B
b10101 C
b10100 D
b10011 E
b10010 F
b10001 G
b10000 H
b1111 I
b1110 !
b1110 -
b0 .
1$
#510
0$
#515
b1111 /
b1110 0
b1101 1
b1100 2
b1011 3
b1010 4
b1001 5
b1000 6
b111 7
b11100 8
b11100 9
b11100 :
b11100 ;
b11100 <
b11100 =
b11011 >
b11010 ?
b11001 @
b11000 A
b10111 B
b10110 C
b10101 D
b10100 E
b10011 F
b10010 G
b10001 H
b10000 I
b1111 !
b1111 -
b0 .
1$
#520
0$
#525
b10000 /
b1111 0
b1110 1
b1101 2
b1100 3
b1011 4
b1010 5
b1001 6
b1000 7
b111 8
b11100 9
b11100 :
b11100 ;
b11100 <
b11100 =
b11100 >
b11011 ?
b11010 @
b11001 A
b11000 B
b10111 C
b10110 D
b10101 E
b10100 F
b10011 G
b10010 H
b10001 I
b10000 !
b10000 -
b0 .
1$
#530
0$
#535
b10001 /
b10000 0
b1111 1
b1110 2
b1101 3
b1100 4
b1011 5
b1010 6
b1001 7
b1000 8
b111 9
b11100 :
b11100 ;
b11100 <
b11100 =
b11100 >
b11100 ?
b11011 @
b11010 A
b11001 B
b11000 C
b10111 D
b10110 E
b10101 F
b10100 G
b10011 H
b10010 I
b10001 !
b10001 -
b0 .
1$
#540
0$
#545
b10010 /
b10001 0
b10000 1
b1111 2
b1110 3
b1101 4
b1100 5
b1011 6
b1010 7
b1001 8
b1000 9
b111 :
b11100 ;
b11100 <
b11100 =
b11100 >
b11100 ?
b11100 @
b11011 A
b11010 B
b11001 C
b11000 D
b10111 E
b10110 F
b10101 G
b10100 H
b10011 I
b10010 !
b10010 -
b0 .
1$
#550
0$
#555
b10011 /
b10010 0
b10001 1
b10000 2
b1111 3
b1110 4
b1101 5
b1100 6
b1011 7
b1010 8
b1001 9
b1000 :
b111 ;
b11100 <
b11100 =
b11100 >
b11100 ?
b11100 @
b11100 A
b11011 B
b11010 C
b11001 D
b11000 E
b10111 F
b10110 G
b10101 H
b10100 I
b10011 !
b10011 -
b0 .
1$
#560
0$
#565
b10100 /
b10011 0
b10010 1
b10001 2
b10000 3
b1111 4
b1110 5
b1101 6
b1100 7
b1011 8
b1010 9
b1001 :
b1000 ;
b111 <
b11100 =
b11100 >
b11100 ?
b11100 @
b11100 A
b11100 B
b11011 C
b11010 D
b11001 E
b11000 F
b10111 G
b10110 H
b10101 I
b10100 !
b10100 -
b0 .
1$
#570
0$
#575
b10101 /
b10100 0
b10011 1
b10010 2
b10001 3
b10000 4
b1111 5
b1110 6
b1101 7
b1100 8
b1011 9
b1010 :
b1001 ;
b1000 <
b111 =
b11100 >
b11100 ?
b11100 @
b11100 A
b11100 B
b11100 C
b11011 D
b11010 E
b11001 F
b11000 G
b10111 H
b10110 I
b10101 !
b10101 -
b0 .
1$
#580
0$
#585
b10110 /
b10101 0
b10100 1
b10011 2
b10010 3
b10001 4
b10000 5
b1111 6
b1110 7
b1101 8
b1100 9
b1011 :
b1010 ;
b1001 <
b1000 =
b111 >
b11100 ?
b11100 @
b11100 A
b11100 B
b11100 C
b11100 D
b11011 E
b11010 F
b11001 G
b11000 H
b10111 I
b10110 !
b10110 -
b0 .
1$
#590
0$
#595
b10111 /
b10110 0
b10101 1
b10100 2
b10011 3
b10010 4
b10001 5
b10000 6
b1111 7
b1110 8
b1101 9
b1100 :
b1011 ;
b1010 <
b1001 =
b1000 >
b111 ?
b11100 @
b11100 A
b11100 B
b11100 C
b11100 D
b11100 E
b11011 F
b11010 G
b11001 H
b11000 I
b10111 !
b10111 -
b0 .
1$
#600
0$
#605
b11000 /
b10111 0
b10110 1
b10101 2
b10100 3
b10011 4
b10010 5
b10001 6
b10000 7
b1111 8
b1110 9
b1101 :
b1100 ;
b1011 <
b1010 =
b1001 >
b1000 ?
b111 @
b11100 A
b11100 B
b11100 C
b11100 D
b11100 E
b11100 F
b11011 G
b11010 H
b11001 I
b11000 !
b11000 -
b0 .
1$
#610
0$
#615
b11001 /
b11000 0
b10111 1
b10110 2
b10101 3
b10100 4
b10011 5
b10010 6
b10001 7
b10000 8
b1111 9
b1110 :
b1101 ;
b1100 <
b1011 =
b1010 >
b1001 ?
b1000 @
b111 A
b11100 B
b11100 C
b11100 D
b11100 E
b11100 F
b11100 G
b11011 H
b11010 I
b11001 !
b11001 -
b0 .
1$
#620
0$
