systolic_array_synthesis/PE.v
module PE #(parameter DATA_WIDTH = 8) (
	input clk,
	input rst_n,
	input  [DATA_WIDTH - 1 : 0]  top_in,
	input  [DATA_WIDTH - 1 : 0]  left_in,
	output reg [DATA_WIDTH - 1 : 0]  right_out,
	output reg [DATA_WIDTH - 1 : 0]  bottom_out,
	output reg  [DATA_WIDTH*2 - 1 : 0] result
);

wire [DATA_WIDTH*2 - 1 : 0] mul;

always @(posedge clk or negedge rst_n) begin
	if(!rst_n) begin
		result     <= 16'b0;
		right_out  <= 8'b0 ;
		bottom_out <= 8'b0 ;
	end
	else begin
		result     <= result + mul;
		right_out  <= left_in;
		bottom_out <= top_in;
	end
end

assign mul = top_in * left_in;

endmodule

systolic_array_synthesis/PE_tb.v
`timescale 1ns / 1ps

module PE_tb;
    parameter DATA_WIDTH = 8;

    reg clk;
    reg rst_n;
    reg [DATA_WIDTH - 1 : 0] top_in;
    reg [DATA_WIDTH - 1 : 0] left_in;
    wire [DATA_WIDTH - 1 : 0] right_out;
    wire [DATA_WIDTH - 1 : 0] bottom_out;
    wire [DATA_WIDTH*2 - 1 : 0] result;

    PE #(.DATA_WIDTH (DATA_WIDTH)) dut (
        .clk (clk),
        .rst_n (rst_n),
        .top_in (top_in),
        .left_in (left_in),
        .right_out (right_out),
        .bottom_out (bottom_out),
        .result (result)
    );

    always #5 clk = ~clk;

    reg [DATA_WIDTH - 1 : 0] test_top_in [3:0];
    reg [DATA_WIDTH - 1 : 0] test_left_in [3:0]; 
    reg [DATA_WIDTH*2 - 1 : 0] golden_result [3:0];

    integer i;

    initial begin
        clk = 0;
        rst_n = 0;
        top_in = 0;
        left_in = 0;

        test_top_in[0] = 8'd2;  test_left_in[0] = 8'd3;   golden_result[0] = 16'd6;
        test_top_in[1] = 8'd4;  test_left_in[1] = 8'd5;   golden_result[1] = 16'd26; // 6+20
        test_top_in[2] = 8'd1;  test_left_in[2] = 8'd10;  golden_result[2] = 16'd36; // 26+10
        test_top_in[3] = 8'd7;  test_left_in[3] = 8'd2;   golden_result[3] = 16'd50; // 36+14

        #20 rst_n = 1;  

        for (i = 0; i < 4; i = i + 1) begin
            top_in = test_top_in[i];
            left_in = test_left_in[i];

            #10;
            
            if (result !== golden_result[i]) 
                $display("Test %d FAILED: top_in=%d, left_in=%d, Expected=%d, Got=%d", 
                    i, top_in, left_in, golden_result[i], result);
            else 
                $display("Test %d PASSED: top_in=%d, left_in=%d, Result=%d", 
                    i, top_in, left_in, result);
        end

        #50 $finish;
    end

    initial begin
		$dumpfile ("PE.VCD");
		$dumpvars (0, PE_tb); 
    end

endmodule

systolic_array_synthesis/PE.VCD
$date
	Sat Feb 22 00:08:38 2025
$end
$version
	Icarus Verilog
$end
$timescale
	1ps
$end
$scope module PE_tb $end
$var wire 8 ! right_out [7:0] $end
$var wire 16 " result [15:0] $end
$var wire 8 # bottom_out [7:0] $end
$var parameter 32 $ DATA_WIDTH $end
$var reg 1 % clk $end
$var reg 8 & left_in [7:0] $end
$var reg 1 ' rst_n $end
$var reg 8 ( top_in [7:0] $end
$var integer 32 ) i [31:0] $end
$scope module dut $end
$var wire 1 % clk $end
$var wire 8 * left_in [7:0] $end
$var wire 1 ' rst_n $end
$var wire 8 + top_in [7:0] $end
$var wire 16 , mul [15:0] $end
$var parameter 32 - DATA_WIDTH $end
$var reg 8 . bottom_out [7:0] $end
$var reg 16 / result [15:0] $end
$var reg 8 0 right_out [7:0] $end
$upscope $end
$upscope $end
$enddefinitions $end
$comment Show the parameter values. $end
$dumpall
b1000 -
b1000 $
$end
#0
$dumpvars
b0 0
b0 /
b0 .
b0 ,
b0 +
b0 *
bx )
b0 (
0'
b0 &
0%
b0 #
b0 "
b0 !
$end
#5000
1%
#10000
0%
#15000
1%
#20000
b110 ,
0%
b11 &
b11 *
b10 (
b10 +
b0 )
1'
#25000
b10 #
b10 .
b11 !
b11 0
b110 "
b110 /
1%
#30000
b10100 ,
0%
b101 &
b101 *
b100 (
b100 +
b1 )
#35000
b100 #
b100 .
b101 !
b101 0
b11010 "
b11010 /
1%
#40000
b1010 ,
0%
b1010 &
b1010 *
b1 (
b1 +
b10 )
#45000
b1 #
b1 .
b1010 !
b1010 0
b100100 "
b100100 /
1%
#50000
b1110 ,
0%
b10 &
b10 *
b111 (
b111 +
b11 )
#55000
b111 #
b111 .
b10 !
b10 0
b110010 "
b110010 /
1%
#60000
0%
b100 )
#65000
b1000000 "
b1000000 /
1%
#70000
0%
#75000
b1001110 "
b1001110 /
1%
#80000
0%
#85000
b1011100 "
b1011100 /
1%
#90000
0%
#95000
b1101010 "
b1101010 /
1%
#100000
0%
#105000
b1111000 "
b1111000 /
1%
