systolic_array_32x32x3/ifm_addr_controller.v
module ifm_addr_controller #(
    parameter KERNEL_SIZE = 3   ,
    parameter IFM_SIZE    = 34  ,
    parameter IFM_CHANNEL = 3   ,
    parameter ADDR_WIDTH  = 19
) (
    input                           clk       ,
    input                           rst_n     ,
    input                           load      ,
    output reg [ADDR_WIDTH - 1 : 0] ifm_addr  ,
    output reg                      addr_valid
);

    parameter IDLE         = 3'b000 ;
    parameter NEXT_PIXEL   = 3'b001 ;
    parameter NEXT_LINE    = 3'b010 ;
    parameter NEXT_CHANNEL = 3'b011 ;
    parameter NEXT_TILING  = 3'b100 ;

    reg [2:0] current_state, next_state;
    
    reg [ADDR_WIDTH - 1 : 0] base_addr;
    
    reg [1:0] count_pixel_in_row;
    reg [3:0] count_pixel_in_window;
    reg [4:0] count_pixel_in_channel;

    reg [1:0] count_line;
    reg [3:0] count_channel;

    always @(posedge clk or negedge rst_n) begin
        if (!rst_n) current_state <= IDLE;
        else        current_state <= next_state;
    end

    always @(*) begin
        case (current_state)
            IDLE: if (load) next_state = NEXT_PIXEL;
            NEXT_PIXEL: begin
                if      (count_pixel_in_channel == IFM_CHANNEL * KERNEL_SIZE * (KERNEL_SIZE - 1)) next_state = NEXT_TILING;   
                else if (count_pixel_in_window  == KERNEL_SIZE * (KERNEL_SIZE - 1))               next_state = NEXT_CHANNEL;  
                else if (count_pixel_in_row     == KERNEL_SIZE - 1)                               next_state = NEXT_LINE;
            end 
            NEXT_LINE:    next_state = NEXT_PIXEL;
            NEXT_CHANNEL: next_state = NEXT_PIXEL;
            NEXT_TILING:  next_state = IDLE;
            default:      next_state = IDLE;
        endcase
    end

    always @(posedge clk or negedge rst_n) begin
        if (!rst_n) addr_valid <= 0;
        else begin
          case (next_state)
            IDLE:         addr_valid <= 0 ;
            NEXT_PIXEL:   addr_valid <= 1 ;
            NEXT_LINE:    addr_valid <= 1 ;
            NEXT_CHANNEL: addr_valid <= 1 ;
            NEXT_TILING:  addr_valid <= 1 ;
          endcase
        end
    end

    always @(posedge clk or negedge rst_n) begin
        if (!rst_n) begin
            ifm_addr               <= 0 ;
            base_addr              <= 0 ;
            count_pixel_in_row     <= 1 ;
            count_pixel_in_window  <= 1 ;
            count_pixel_in_channel <= 1 ;
            count_line             <= 1 ;
            count_channel          <= 1 ;
        end
        else begin
            case (current_state)
                IDLE: begin
                    ifm_addr               <= base_addr ;
                    count_pixel_in_row     <= 1         ;
                    count_pixel_in_window  <= 1         ;
                    count_pixel_in_channel <= 1         ;
                    count_line             <= 1         ;
                    count_channel          <= 1         ;
                end 
                NEXT_PIXEL: begin
                    ifm_addr               <= ifm_addr + 1               ;
                    count_pixel_in_row     <= count_pixel_in_row + 1     ;
                    count_pixel_in_window  <= count_pixel_in_window + 1  ;
                    count_pixel_in_channel <= count_pixel_in_channel + 1 ;
                end
                NEXT_LINE: begin
                    ifm_addr           <= base_addr + (count_channel - 1) * IFM_SIZE * IFM_SIZE + count_line * IFM_SIZE ;
                    count_line         <= count_line + 1                                                                ;
                    count_pixel_in_row <= 1                                                                             ;
                end
                NEXT_CHANNEL: begin
                    ifm_addr              <= base_addr + count_channel * IFM_SIZE * IFM_SIZE ;
                    count_channel         <= count_channel + 1                               ;
                    count_line            <= 1                                               ; 
                    count_pixel_in_row    <= 1                                               ;
                    count_pixel_in_window <= 1                                               ;
                end
                NEXT_TILING: base_addr <= (((base_addr + 18) % IFM_SIZE) == 0) ? (base_addr + 18) : (base_addr + 16);
            endcase
        end
    end

endmodule

systolic_array_32x32x3_16filters_read_vertically/ifm_addr_controller_tb.v
module ifm_addr_controller_tb();
 
 parameter KERNEL_SIZE = 3   ;
 parameter IFM_SIZE    = 34 ;
 parameter IFM_CHANNEL = 3   ;
 parameter ADDR_WIDTH  = 12  ;
 
 reg                       clk        ;
 reg                       rst_n      ;
 reg                       load       ;
 wire [ADDR_WIDTH - 1 : 0] ifm_addr   ;
 wire                      addr_valid ;
 
 ifm_addr_controller #(
     .KERNEL_SIZE ( KERNEL_SIZE ) ,
     .IFM_SIZE    ( IFM_SIZE    ) ,
     .IFM_CHANNEL ( IFM_CHANNEL ) ,
     .ADDR_WIDTH  ( ADDR_WIDTH  )
 ) ifm_addr_dut (
     .clk        ( clk        ) ,
     .rst_n      ( rst_n      ) ,
     .load       ( load       ) ,
     .ifm_addr   ( ifm_addr   ) ,
     .addr_valid ( addr_valid )
 );
 
 always #5 clk = ~clk;
 
 initial begin
     clk = 0;
     rst_n = 0;
     load = 0;
 
     #30 rst_n = 1; load = 1;
     #10000 $finish;
 end
 
 initial begin
     $dumpfile ("ifm_addr_controller.VCD");
     $dumpvars (0, ifm_addr_controller_tb);
 end
 
 endmodule

systolic_array_primitives/ifm_addr_controller.VCD
$date
	Fri Mar 21 06:06:31 2025
$end
$version
	Icarus Verilog
$end
$timescale
	1s
$end
$scope module ifm_addr_controller_tb $end
$var wire 19 ! ifm_addr [18:0] $end
$var wire 1 " addr_valid $end
$var parameter 32 # ADDR_WIDTH $end
$var parameter 32 $ IFM_CHANNEL $end
$var parameter 32 % IFM_SIZE $end
$var parameter 32 & KERNEL_SIZE $end
$var reg 1 ' clk $end
$var reg 1 ( load $end
$var reg 1 ) rst_n $end
$scope module ifm_addr_dut $end
$var wire 1 ' clk $end
$var wire 1 ( load $end
$var wire 1 ) rst_n $end
$var parameter 32 * ADDR_WIDTH $end
$var parameter 3 + IDLE $end
$var parameter 32 , IFM_CHANNEL $end
$var parameter 32 - IFM_SIZE $end
$var parameter 32 . KERNEL_SIZE $end
$var parameter 3 / NEXT_CHANNEL $end
$var parameter 3 0 NEXT_LINE $end
$var parameter 3 1 NEXT_PIXEL $end
$var parameter 3 2 NEXT_TILING $end
$var reg 1 " addr_valid $end
$var reg 19 3 base_addr [18:0] $end
$var reg 4 4 count_channel [3:0] $end
$var reg 2 5 count_line [1:0] $end
$var reg 5 6 count_pixel_in_channel [4:0] $end
$var reg 2 7 count_pixel_in_row [1:0] $end
$var reg 4 8 count_pixel_in_window [3:0] $end
$var reg 3 9 current_state [2:0] $end
$var reg 19 : ifm_addr [18:0] $end
$var reg 3 ; next_state [2:0] $end
$upscope $end
$upscope $end
$enddefinitions $end
$comment Show the parameter values. $end
$dumpall
b100 2
b1 1
b10 0
b11 /
b11 .
b110100000 -
b11 ,
b0 +
b10011 *
b11 &
b110100000 %
b11 $
b10011 #
$end
#0
$dumpvars
b0 ;
b0 :
b0 9
b1 8
b1 7
b1 6
b1 5
b1 4
b0 3
0)
0(
0'
0"
b0 !
$end
#5
1'
#10
0'
#15
1'
#20
0'
#25
1'
#30
b1 ;
0'
1(
1)
#35
b1 9
1"
1'
#40
0'
#45
b10 ;
b10 6
b10 8
b10 7
b1 !
b1 :
1'
#50
0'
#55
b1 ;
b10 9
b11 6
b11 8
b11 7
b10 !
b10 :
1'
#60
0'
#65
b1 7
b10 5
b110100000 !
b110100000 :
b1 9
1'
#70
0'
#75
b10 ;
b100 6
b100 8
b10 7
b110100001 !
b110100001 :
1'
#80
0'
#85
b1 ;
b101 6
b101 8
b11 7
b110100010 !
b110100010 :
b10 9
1'
#90
0'
#95
b1 9
b1 7
b11 5
b1101000000 !
b1101000000 :
1'
#100
0'
#105
b11 ;
b110 6
b110 8
b10 7
b1101000001 !
b1101000001 :
1'
#110
0'
#115
b1 ;
b11 9
b111 6
b111 8
b11 7
b1101000010 !
b1101000010 :
1'
#120
0'
#125
b1 8
b1 7
b1 5
b10 4
b101010010000000000 !
b101010010000000000 :
b1 9
1'
#130
0'
#135
b10 ;
b1000 6
b10 8
b10 7
b101010010000000001 !
b101010010000000001 :
1'
#140
0'
#145
b1 ;
b1001 6
b11 8
b11 7
b101010010000000010 !
b101010010000000010 :
b10 9
1'
#150
0'
#155
b1 9
b1 7
b10 5
b101010010110100000 !
b101010010110100000 :
1'
#160
0'
#165
b10 ;
b1010 6
b100 8
b10 7
b101010010110100001 !
b101010010110100001 :
1'
#170
0'
#175
b1 ;
b10 9
b1011 6
b101 8
b11 7
b101010010110100010 !
b101010010110100010 :
1'
#180
0'
#185
b1 7
b11 5
b101010011101000000 !
b101010011101000000 :
b1 9
1'
#190
0'
#195
b11 ;
b1100 6
b110 8
b10 7
b101010011101000001 !
b101010011101000001 :
1'
#200
0'
#205
b1 ;
b1101 6
b111 8
b11 7
b101010011101000010 !
b101010011101000010 :
b11 9
1'
#210
0'
#215
b1 9
b1 8
b1 7
b1 5
b11 4
b1010100100000000000 !
b1010100100000000000 :
1'
#220
0'
#225
b10 ;
b1110 6
b10 8
b10 7
b1010100100000000001 !
b1010100100000000001 :
1'
#230
0'
#235
b1 ;
b10 9
b1111 6
b11 8
b11 7
b1010100100000000010 !
b1010100100000000010 :
1'
#240
0'
#245
b1 7
b10 5
b1010100100110100000 !
b1010100100110100000 :
b1 9
1'
#250
0'
#255
b10 ;
b10000 6
b100 8
b10 7
b1010100100110100001 !
b1010100100110100001 :
1'
#260
0'
#265
b1 ;
b10001 6
b101 8
b11 7
b1010100100110100010 !
b1010100100110100010 :
b10 9
1'
#270
0'
#275
b1 9
b1 7
b11 5
b1010100101101000000 !
b1010100101101000000 :
1'
#280
0'
#285
b100 ;
b10010 6
b110 8
b10 7
b1010100101101000001 !
b1010100101101000001 :
1'
#290
0'
#295
b0 ;
b100 9
b10011 6
b111 8
b11 7
b1010100101101000010 !
b1010100101101000010 :
1'
#300
0'
#305
b1 ;
b10000 3
0"
b0 9
1'
#310
0'
#315
b1 9
1"
b1 4
b1 5
b1 6
b1 8
b1 7
b10000 !
b10000 :
1'
#320
0'
#325
b10 ;
b10 6
b10 8
b10 7
b10001 !
b10001 :
1'
#330
0'
#335
b1 ;
b10 9
b11 6
b11 8
b11 7
b10010 !
b10010 :
1'
#340
0'
#345
b1 7
b10 5
b110110000 !
b110110000 :
b1 9
1'
#350
0'
#355
b10 ;
b100 6
b100 8
b10 7
b110110001 !
b110110001 :
1'
#360
0'
#365
b1 ;
b101 6
b101 8
b11 7
b110110010 !
b110110010 :
b10 9
1'
#370
0'
#375
b1 9
b1 7
b11 5
b1101010000 !
b1101010000 :
1'
#380
0'
#385
b11 ;
b110 6
b110 8
b10 7
b1101010001 !
b1101010001 :
1'
#390
0'
#395
b1 ;
b11 9
b111 6
b111 8
b11 7
b1101010010 !
b1101010010 :
1'
#400
0'
#405
b1 8
b1 7
b1 5
b10 4
b101010010000010000 !
b101010010000010000 :
b1 9
1'
#410
0'
#415
b10 ;
b1000 6
b10 8
b10 7
b101010010000010001 !
b101010010000010001 :
1'
#420
0'
#425
b1 ;
b1001 6
b11 8
b11 7
b101010010000010010 !
b101010010000010010 :
b10 9
1'
#430
0'
#435
b1 9
b1 7
b10 5
b101010010110110000 !
b101010010110110000 :
1'
#440
0'
#445
b10 ;
b1010 6
b100 8
b10 7
b101010010110110001 !
b101010010110110001 :
1'
#450
0'
#455
b1 ;
b10 9
b1011 6
b101 8
b11 7
b101010010110110010 !
b101010010110110010 :
1'
#460
0'
#465
b1 7
b11 5
b101010011101010000 !
b101010011101010000 :
b1 9
1'
#470
0'
#475
b11 ;
b1100 6
b110 8
b10 7
b101010011101010001 !
b101010011101010001 :
1'
#480
0'
#485
b1 ;
b1101 6
b111 8
b11 7
b101010011101010010 !
b101010011101010010 :
b11 9
1'
#490
0'
#495
b1 9
b1 8
b1 7
b1 5
b11 4
b1010100100000010000 !
b1010100100000010000 :
1'
#500
0'
#505
b10 ;
b1110 6
b10 8
b10 7
b1010100100000010001 !
b1010100100000010001 :
1'
#510
0'
#515
b1 ;
b10 9
b1111 6
b11 8
b11 7
b1010100100000010010 !
b1010100100000010010 :
1'
#520
0'
#525
b1 7
b10 5
b1010100100110110000 !
b1010100100110110000 :
b1 9
1'
#530
0'
#535
b10 ;
b10000 6
b100 8
b10 7
b1010100100110110001 !
b1010100100110110001 :
1'
#540
0'
#545
b1 ;
b10001 6
b101 8
b11 7
b1010100100110110010 !
b1010100100110110010 :
b10 9
1'
#550
0'
#555
b1 9
b1 7
b11 5
b1010100101101010000 !
b1010100101101010000 :
1'
#560
0'
#565
b100 ;
b10010 6
b110 8
b10 7
b1010100101101010001 !
b1010100101101010001 :
1'
#570
0'
#575
b0 ;
b100 9
b10011 6
b111 8
b11 7
b1010100101101010010 !
b1010100101101010010 :
1'
#580
0'
#585
b1 ;
b100000 3
0"
b0 9
1'
#590
0'
#595
b1 9
1"
b1 4
b1 5
b1 6
b1 8
b1 7
b100000 !
b100000 :
1'
#600
0'
#605
b10 ;
b10 6
b10 8
b10 7
b100001 !
b100001 :
1'
#610
0'
#615
b1 ;
b10 9
b11 6
b11 8
b11 7
b100010 !
b100010 :
1'
#620
0'
#625
b1 7
b10 5
b111000000 !
b111000000 :
b1 9
1'
#630
0'
#635
b10 ;
b100 6
b100 8
b10 7
b111000001 !
b111000001 :
1'
#640
0'
#645
b1 ;
b101 6
b101 8
b11 7
b111000010 !
b111000010 :
b10 9
1'
#650
0'
#655
b1 9
b1 7
b11 5
b1101100000 !
b1101100000 :
1'
#660
0'
#665
b11 ;
b110 6
b110 8
b10 7
b1101100001 !
b1101100001 :
1'
#670
0'
#675
b1 ;
b11 9
b111 6
b111 8
b11 7
b1101100010 !
b1101100010 :
1'
#680
0'
#685
b1 8
b1 7
b1 5
b10 4
b101010010000100000 !
b101010010000100000 :
b1 9
1'
#690
0'
#695
b10 ;
b1000 6
b10 8
b10 7
b101010010000100001 !
b101010010000100001 :
1'
#700
0'
#705
b1 ;
b1001 6
b11 8
b11 7
b101010010000100010 !
b101010010000100010 :
b10 9
1'
#710
0'
#715
b1 9
b1 7
b10 5
b101010010111000000 !
b101010010111000000 :
1'
#720
0'
#725
b10 ;
b1010 6
b100 8
b10 7
b101010010111000001 !
b101010010111000001 :
1'
#730
0'
#735
b1 ;
b10 9
b1011 6
b101 8
b11 7
b101010010111000010 !
b101010010111000010 :
1'
#740
0'
#745
b1 7
b11 5
b101010011101100000 !
b101010011101100000 :
b1 9
1'
#750
0'
#755
b11 ;
b1100 6
b110 8
b10 7
b101010011101100001 !
b101010011101100001 :
1'
#760
0'
#765
b1 ;
b1101 6
b111 8
b11 7
b101010011101100010 !
b101010011101100010 :
b11 9
1'
#770
0'
#775
b1 9
b1 8
b1 7
b1 5
b11 4
b1010100100000100000 !
b1010100100000100000 :
1'
#780
0'
#785
b10 ;
b1110 6
b10 8
b10 7
b1010100100000100001 !
b1010100100000100001 :
1'
#790
0'
#795
b1 ;
b10 9
b1111 6
b11 8
b11 7
b1010100100000100010 !
b1010100100000100010 :
1'
#800
0'
#805
b1 7
b10 5
b1010100100111000000 !
b1010100100111000000 :
b1 9
1'
#810
0'
#815
b10 ;
b10000 6
b100 8
b10 7
b1010100100111000001 !
b1010100100111000001 :
1'
#820
0'
#825
b1 ;
b10001 6
b101 8
b11 7
b1010100100111000010 !
b1010100100111000010 :
b10 9
1'
#830
0'
#835
b1 9
b1 7
b11 5
b1010100101101100000 !
b1010100101101100000 :
1'
#840
0'
#845
b100 ;
b10010 6
b110 8
b10 7
b1010100101101100001 !
b1010100101101100001 :
1'
#850
0'
#855
b0 ;
b100 9
b10011 6
b111 8
b11 7
b1010100101101100010 !
b1010100101101100010 :
1'
#860
0'
#865
b1 ;
b110000 3
0"
b0 9
1'
#870
0'
#875
b1 9
1"
b1 4
b1 5
b1 6
b1 8
b1 7
b110000 !
b110000 :
1'
#880
0'
#885
b10 ;
b10 6
b10 8
b10 7
b110001 !
b110001 :
1'
#890
0'
#895
b1 ;
b10 9
b11 6
b11 8
b11 7
b110010 !
b110010 :
1'
#900
0'
#905
b1 7
b10 5
b111010000 !
b111010000 :
b1 9
1'
#910
0'
#915
b10 ;
b100 6
b100 8
b10 7
b111010001 !
b111010001 :
1'
#920
0'
#925
b1 ;
b101 6
b101 8
b11 7
b111010010 !
b111010010 :
b10 9
1'
#930
0'
#935
b1 9
b1 7
b11 5
b1101110000 !
b1101110000 :
1'
#940
0'
#945
b11 ;
b110 6
b110 8
b10 7
b1101110001 !
b1101110001 :
1'
#950
0'
#955
b1 ;
b11 9
b111 6
b111 8
b11 7
b1101110010 !
b1101110010 :
1'
#960
0'
#965
b1 8
b1 7
b1 5
b10 4
b101010010000110000 !
b101010010000110000 :
b1 9
1'
#970
0'
#975
b10 ;
b1000 6
b10 8
b10 7
b101010010000110001 !
b101010010000110001 :
1'
#980
0'
#985
b1 ;
b1001 6
b11 8
b11 7
b101010010000110010 !
b101010010000110010 :
b10 9
1'
#990
0'
#995
b1 9
b1 7
b10 5
b101010010111010000 !
b101010010111010000 :
1'
#1000
0'
#1005
b10 ;
b1010 6
b100 8
b10 7
b101010010111010001 !
b101010010111010001 :
1'
#1010
0'
#1015
b1 ;
b10 9
b1011 6
b101 8
b11 7
b101010010111010010 !
b101010010111010010 :
1'
#1020
0'
#1025
b1 7
b11 5
b101010011101110000 !
b101010011101110000 :
b1 9
1'
