systolic_array_primitives/wgt_addr_controller.v
module wgt_addr_controller #(
    parameter KERNEL_SIZE = 3 ,
    parameter NO_CHANNEL  = 3 ,
    parameter ADDR_WIDTH  = 9
) (
    input                           clk       ,
    input                           rst_n     ,
    input                           load      ,
    output reg [ADDR_WIDTH - 1 : 0] wgt_addr  ,
    output reg                      addr_valid
);

    parameter IDLE       = 1'b0 ;
    parameter ADDRESSING = 1'b1 ;

    reg current_state, next_state;

    reg [4:0] count;

    always @(posedge clk or negedge rst_n) begin
        if (!rst_n) current_state <= IDLE;
        else        current_state <= next_state;
    end

    always @(*) begin
        case (current_state)
            IDLE:       if (load)                                            next_state = ADDRESSING;
            ADDRESSING: if (count == KERNEL_SIZE * KERNEL_SIZE * NO_CHANNEL) next_state = IDLE;
            default:    next_state = IDLE;
        endcase
    end

    always @(posedge clk or negedge rst_n) begin
        if (!rst_n) addr_valid <= 0;
        else begin
          case (next_state)
            IDLE:       addr_valid <= 0 ;
            ADDRESSING: addr_valid <= 1 ;
          endcase
        end
    end

    always @(posedge clk or negedge rst_n) begin
        if (!rst_n) begin
            wgt_addr <= 0 ; 
            count    <= 1 ;
        end
        else begin
            case (current_state)
                IDLE: begin
                    wgt_addr <= wgt_addr ;
                    count    <= 1        ;
                end
                ADDRESSING: begin
                    wgt_addr <= wgt_addr + 16 ;
                    count    <= count + 1     ;
                end
            endcase
        end
    end

endmodule

systolic_array_layer0/wgt_addr_controller_tb.v
module wgt_addr_controller_tb();

parameter KERNEL_SIZE = 3  ;
parameter NO_CHANNEL  = 3  ;
parameter ADDR_WIDTH  = 11 ;

reg                       clk        ;
reg                       rst_n      ;
reg                       load       ;
wire [ADDR_WIDTH - 1 : 0] wgt_addr   ;
wire                      addr_valid ;

wgt_addr_controller #(
    .KERNEL_SIZE ( KERNEL_SIZE ) ,
    .NO_CHANNEL  ( NO_CHANNEL  ) ,
    .ADDR_WIDTH  ( ADDR_WIDTH  )
) wgt_addr_dut (
    .clk        ( clk        ) ,
    .rst_n      ( rst_n      ) ,
    .load       ( load       ) ,
    .wgt_addr   ( wgt_addr   ) ,
    .addr_valid ( addr_valid )
);

always #5 clk = ~clk;

initial begin
    clk = 0;
    rst_n = 0;
    load = 0;

    #30 rst_n = 1; load = 1;
    #50 load = 0;
    #250 load = 1;
    #500 $finish;
end

initial begin
    $dumpfile ("wgt_addr_controller.VCD");
    $dumpvars (0, wgt_addr_controller_tb);
end

endmodule

systolic_array_primitives/wgt_addr_controller.VCD
$date
	Fri Mar 21 07:22:11 2025
$end
$version
	Icarus Verilog
$end
$timescale
	1s
$end
$scope module wgt_addr_controller_tb $end
$var wire 11 ! wgt_addr [10:0] $end
$var wire 1 " addr_valid $end
$var parameter 32 # ADDR_WIDTH $end
$var parameter 32 $ KERNEL_SIZE $end
$var parameter 32 % NO_CHANNEL $end
$var reg 1 & clk $end
$var reg 1 ' load $end
$var reg 1 ( rst_n $end
$scope module wgt_addr_dut $end
$var wire 1 & clk $end
$var wire 1 ' load $end
$var wire 1 ( rst_n $end
$var parameter 1 ) ADDRESSING $end
$var parameter 32 * ADDR_WIDTH $end
$var parameter 1 + IDLE $end
$var parameter 32 , KERNEL_SIZE $end
$var parameter 32 - NO_CHANNEL $end
$var reg 1 " addr_valid $end
$var reg 5 . count [4:0] $end
$var reg 1 / current_state $end
$var reg 1 0 next_state $end
$var reg 11 1 wgt_addr [10:0] $end
$upscope $end
$upscope $end
$enddefinitions $end
$comment Show the parameter values. $end
$dumpall
b11 -
b11 ,
0+
b1011 *
1)
b11 %
b11 $
b1011 #
$end
#0
$dumpvars
b0 1
00
0/
b1 .
0(
0'
0&
0"
b0 !
$end
#5
1&
#10
0&
#15
1&
#20
0&
#25
1&
#30
10
0&
1'
1(
#35
1/
1"
1&
#40
0&
#45
b10 .
b10000 !
b10000 1
1&
#50
0&
#55
b11 .
b100000 !
b100000 1
1&
#60
0&
#65
b100 .
b110000 !
b110000 1
1&
#70
0&
#75
b101 .
b1000000 !
b1000000 1
1&
#80
0&
0'
#85
b110 .
b1010000 !
b1010000 1
1&
#90
0&
#95
b111 .
b1100000 !
b1100000 1
1&
#100
0&
#105
b1000 .
b1110000 !
b1110000 1
1&
#110
0&
#115
b1001 .
b10000000 !
b10000000 1
1&
#120
0&
#125
b1010 .
b10010000 !
b10010000 1
1&
#130
0&
#135
b1011 .
b10100000 !
b10100000 1
1&
#140
0&
#145
b1100 .
b10110000 !
b10110000 1
1&
#150
0&
#155
b1101 .
b11000000 !
b11000000 1
1&
#160
0&
#165
b1110 .
b11010000 !
b11010000 1
1&
#170
0&
#175
b1111 .
b11100000 !
b11100000 1
1&
#180
0&
#185
b10000 .
b11110000 !
b11110000 1
1&
#190
0&
#195
b10001 .
b100000000 !
b100000000 1
1&
#200
0&
#205
b10010 .
b100010000 !
b100010000 1
1&
#210
0&
#215
b10011 .
b100100000 !
b100100000 1
1&
#220
0&
#225
b10100 .
b100110000 !
b100110000 1
1&
#230
0&
#235
b10101 .
b101000000 !
b101000000 1
1&
#240
0&
#245
b10110 .
b101010000 !
b101010000 1
1&
#250
0&
#255
b10111 .
b101100000 !
b101100000 1
1&
#260
0&
#265
b11000 .
b101110000 !
b101110000 1
1&
#270
0&
#275
b11001 .
b110000000 !
b110000000 1
1&
#280
0&
#285
b11010 .
b110010000 !
b110010000 1
1&
#290
0&
#295
00
b11011 .
b110100000 !
b110100000 1
1&
#300
0&
#305
b11100 .
b110110000 !
b110110000 1
0"
0/
1&
#310
0&
#315
b1 .
1&
#320
0&
#325
1&
#330
10
0&
1'
#335
1/
1"
1&
#340
0&
#345
b10 .
b111000000 !
b111000000 1
1&
#350
0&
#355
b11 .
b111010000 !
b111010000 1
1&
#360
0&
#365
b100 .
b111100000 !
b111100000 1
1&
#370
0&
#375
b101 .
b111110000 !
b111110000 1
1&
#380
0&
#385
b110 .
b1000000000 !
b1000000000 1
1&
#390
0&
#395
b111 .
b1000010000 !
b1000010000 1
1&
#400
0&
#405
b1000 .
b1000100000 !
b1000100000 1
1&
#410
0&
#415
b1001 .
b1000110000 !
b1000110000 1
1&
#420
0&
#425
b1010 .
b1001000000 !
b1001000000 1
1&
#430
0&
#435
b1011 .
b1001010000 !
b1001010000 1
1&
#440
0&
#445
b1100 .
b1001100000 !
b1001100000 1
1&
#450
0&
#455
b1101 .
b1001110000 !
b1001110000 1
1&
#460
0&
#465
b1110 .
b1010000000 !
b1010000000 1
1&
#470
0&
#475
b1111 .
b1010010000 !
b1010010000 1
1&
#480
0&
#485
b10000 .
b1010100000 !
b1010100000 1
1&
#490
0&
#495
b10001 .
b1010110000 !
b1010110000 1
1&
#500
0&
#505
b10010 .
b1011000000 !
b1011000000 1
1&
#510
0&
#515
b10011 .
b1011010000 !
b1011010000 1
1&
#520
0&
#525
b10100 .
b1011100000 !
b1011100000 1
1&
#530
0&
#535
b10101 .
b1011110000 !
b1011110000 1
1&
#540
0&
#545
b10110 .
b1100000000 !
b1100000000 1
1&
#550
0&
#555
b10111 .
b1100010000 !
b1100010000 1
1&
#560
0&
#565
b11000 .
b1100100000 !
b1100100000 1
1&
#570
0&
#575
b11001 .
b1100110000 !
b1100110000 1
1&
#580
0&
#585
b11010 .
b1101000000 !
b1101000000 1
1&
#590
0&
#595
00
b11011 .
b1101010000 !
b1101010000 1
1&
#600
0&
#605
10
b11100 .
b1101100000 !
b1101100000 1
0"
0/
1&
#610
0&
#615
1/
1"
b1 .
1&
#620
0&
#625
b10 .
b1101110000 !
b1101110000 1
1&
#630
0&
#635
b11 .
b1110000000 !
b1110000000 1
1&
#640
0&
#645
b100 .
b1110010000 !
b1110010000 1
1&
#650
0&
#655
b101 .
b1110100000 !
b1110100000 1
1&
#660
0&
#665
b110 .
b1110110000 !
b1110110000 1
1&
#670
0&
#675
b111 .
b1111000000 !
b1111000000 1
1&
#680
0&
#685
b1000 .
b1111010000 !
b1111010000 1
1&
#690
0&
#695
b1001 .
b1111100000 !
b1111100000 1
1&
#700
0&
#705
b1010 .
b1111110000 !
b1111110000 1
1&
#710
0&
#715
b1011 .
b10000000000 !
b10000000000 1
1&
#720
0&
#725
b1100 .
b10000010000 !
b10000010000 1
1&
#730
0&
#735
b1101 .
b10000100000 !
b10000100000 1
1&
#740
0&
#745
b1110 .
b10000110000 !
b10000110000 1
1&
#750
0&
#755
b1111 .
b10001000000 !
b10001000000 1
1&
#760
0&
#765
b10000 .
b10001010000 !
b10001010000 1
1&
#770
0&
#775
b10001 .
b10001100000 !
b10001100000 1
1&
#780
0&
#785
b10010 .
b10001110000 !
b10001110000 1
1&
#790
0&
#795
b10011 .
b10010000000 !
b10010000000 1
1&
#800
0&
#805
b10100 .
b10010010000 !
b10010010000 1
1&
#810
0&
#815
b10101 .
b10010100000 !
b10010100000 1
1&
#820
0&
#825
b10110 .
b10010110000 !
b10010110000 1
1&
